Workbook

Sheet index
C4: Company Name: | D4: Larsen & Toubro Limited (L&T)
C5: Parent Organization: | D5: It is an Independent Company
C6: Headquartes: | D6: Mumbai, Maharashtra, India
C7: Founder: | D7: Henning Holck-Larsen
D8: Søren Kristian Toubro
B13: Sheet No | C13: Sheet Name | D13: Link to Sheet
B14: 1 | C14: Index | D14: Index!A1
B15: 2 | C15: Income Statement Drivers | D15: Income Sheet Drivers'!A1
B16: 3 | C16: Balance Sheet Drivers | D16: Balance Sheet Drivers'!A1
B17: 4 | C17: forcast | D17: forcast!A1
B18: 5 | C18: Inocme Statement | D18: Income Statement'!A1
B19: 6 | C19: Balance Sheet | D19: Balance Sheet'!A1
B20: 7 | C20: Cashflow Statement | D20: Cashflow Statement'!A1
B21: 8 | C21: WACC | D21: Weigheted Average Cost Of Cap..'!A1
B22: 9 | C22: DCF | D22: Discounted Cash Flow Model'!A1
B23: 10 | C23: Comperative Analysis | D23: Comperative Analysis'!A1
B24: 11 | C24: Income Statement Raw Data | D24: IS!A1
B25: 12 | C25: Balance Sheet Raw Data | D25: BS!A1
B26: 13 | C26: Cashflow Statement Raw Data | D26: CF!A1

Sheet p&L drivers
B1: Scenario | C1: 1 | L1: Index!A1
B2: Drivers
B3: All the Figures In Crores
B4: Financial Year | C4: 44389 | D4: =C4+365 -> 44754 | E4: =D4+365 -> 45119 | F4: =E4+365 -> 45484 | G4: =F4+365 -> 45849 | H4: =G4+365 -> 46214 | I4: =H4+365 -> 46579 | J4: =I4+365 -> 46944 | K4: =J4+365 -> 47309 | L4: =K4+365 -> 47674
B5: Income Statement Drivers
B6: Revenue | C6: ='p&l'!C5 -> 135979.03 | D6: ='p&l'!D5 -> 156521.23 | E6: ='p&l'!E5 -> 183340.7 | F6: ='p&l'!F5 -> 221112.91 | G6: ='p&l'!G5 -> 255734.45
B7: Revenue Growth (Y-O-Y %) | C7: =0 -> 0 | D7: =forcast!S12 -> 0.15106744 | E7: =forcast!S13 -> 0.17135081 | F7: =forcast!S14 -> 0.20602048 | G7: =forcast!S15 -> 0.15657605 | H7: =CHOOSE($C$1,H8,H9,H10) -> 0.12465368 | I7: =CHOOSE($C$1,I8,I9,I10) -> 0.12139912 | J7: =CHOOSE($C$1,J8,J9,J10) -> 0.11357381 | K7: =CHOOSE($C$1,K8,K9,K10) -> 0.097773554 | L7: =CHOOSE($C$1,L8,L9,L10) -> 0.088263
B8: Scenario 1 (Pessimistic) | H8: =H9-1% -> 0.12465368 | I8: =I9-1% -> 0.12139912 | J8: =J9-1% -> 0.11357381 | K8: =K9-1% -> 0.097773554 | L8: =L9-1% -> 0.088263
B9: Scenario 2 (Realistic) | H9: =forcast!N22 -> 0.13465368 | I9: =forcast!N23 -> 0.13139912 | J9: =forcast!N24 -> 0.12357381 | K9: =forcast!N25 -> 0.10777355 | L9: =forcast!N26 -> 0.098263
B10: Scenario 3 (Optimistic) | H10: =H9+1% -> 0.14465368 | I10: =I9+1% -> 0.14139912 | J10: =J9+1% -> 0.13357381 | K10: =K9+1% -> 0.11777355 | L10: =L9+1% -> 0.108263
B12: Cost of Goods Sold (COGS)
B13: Cogs | C13: ='income statement'!C9 -> 79009.86 | D13: ='income statement'!D9 -> 93785.97 | E13: ='income statement'!E9 -> 110588.83 | F13: ='income statement'!F9 -> 140313.92 | G13: ='income statement'!G9 -> 164670.67 | H13: =CHOOSE($C$1,H14,H15,H16) -> 0.64238305 | I13: =CHOOSE($C$1,I14,I15,I16) -> 0.64865077 | J13: =CHOOSE($C$1,J14,J15,J16) -> 0.6525429 | K13: =CHOOSE($C$1,K14,K15,K16) -> 0.65641397 | L13: =CHOOSE($C$1,L14,L15,L16) -> 0.65478069
B14: Scenario 1 (Pessimistic) | H14: =H15+3% -> 0.64238305 | I14: =I15+3% -> 0.64865077 | J14: =J15+3% -> 0.6525429 | K14: =K15+3% -> 0.65641397 | L14: =L15+3% -> 0.65478069
B15: COGS % of Revenue (Scenario 2 (Base ) | C15: =C13/C6 -> 0.58104444 | D15: =D13/D6 -> 0.59919009 | E15: =E13/E6 -> 0.60318756 | F15: =F13/F6 -> 0.63458041 | G15: =G13/G6 -> 0.64391274 | H15: =AVERAGE(C15:G15) -> 0.61238305 | I15: =AVERAGE(D15:H15) -> 0.61865077 | J15: =AVERAGE(E15:I15) -> 0.6225429 | K15: =AVERAGE(F15:J15) -> 0.62641397 | L15: =AVERAGE(G15:K15) -> 0.62478069
B16: Scenario 3 (Optimistic) | H16: =H15-2% -> 0.59238305 | I16: =I15-2% -> 0.59865077 | J16: =J15-2% -> 0.6025429 | K16: =K15-2% -> 0.60641397 | L16: =L15-2% -> 0.60478069
B18: Operating & Non-Operating Expenses
B19: Employee benefits expense (Growth Y-O-Y) | D19: ='income statement'!D11/'income statement'!C11-1 -> 0.20132854 | E19: ='income statement'!E11/'income statement'!D11-1 -> 0.25158735 | F19: ='income statement'!F11/'income statement'!E11-1 -> 0.10632822 | G19: ='income statement'!G11/'income statement'!F11-1 -> 0.13596117 | H19: =AVERAGE(D19:G19) -> 0.17380132 | I19: =H19 -> 0.17380132 | J19: =I19 -> 0.17380132 | K19: =J19 -> 0.17380132 | L19: =K19 -> 0.17380132
B20: Sales, administration and other expenses (Growth Y-O-Y) | D20: ='income statement'!D13/'income statement'!C13-1 -> -0.0080417904 | E20: ='income statement'!E13/'income statement'!D13-1 -> -0.0083617436 | F20: ='income statement'!F13/'income statement'!E13-1 -> 0.18969769 | G20: ='income statement'!G13/'income statement'!F13-1 -> 0.10928727 | H20: =G20 -> 0.10928727 | I20: =H20 -> 0.10928727 | J20: =I20 -> 0.10928727 | K20: =J20 -> 0.10928727 | L20: =K20 -> 0.10928727
B22: Finance cost of financial services business and finance lease activity | C22: ='income statement'!C12 -> 7691.04 | D22: ='income statement'!D12 -> 5952.54 | E22: ='income statement'!E12 -> 6026.44 | F22: ='income statement'!F12 -> 5714.9 | G22: ='income statement'!G12 -> 6302.23 | H22: =G22 -> 6302.23 | I22: =H22 -> 6302.23 | J22: =I22 -> 6302.23 | K22: =J22 -> 6302.23 | L22: =K22 -> 6302.23
B24: Tax Expenses | C24: ='income statement'!C20 -> 4010.82 | D24: ='income statement'!D20 -> 4216.61 | E24: ='income statement'!E20 -> 4484.16 | F24: ='income statement'!F20 -> 4947.39 | G24: ='income statement'!G20 -> 5891.4 | H24: =H25*H26 -> 7427.506 | I24: =I25*I26 -> 7501.3796 | J24: =J25*J26 -> 7366.1959 | K24: =K25*K26 -> 6456.9539 | L24: =L25*L26 -> 5421.6709
B25: Profit Before Tax | C25: ='income statement'!C19 -> 12235.8 | D25: ='income statement'!D19 -> 14410.73 | E25: ='income statement'!E19 -> 16973.04 | F25: ='income statement'!F19 -> 20423.5 | G25: ='income statement'!G19 -> 23104.01 | H25: ='income statement'!H19 -> 28113.929 | I25: ='income statement'!I19 -> 28393.549 | J25: ='income statement'!J19 -> 27881.864 | ... L25: ='income statement'!L19 -> 20521.622
B26: Tax Rate | C26: =C24/C25 -> 0.32779385 | D26: =D24/D25 -> 0.29260211 | E26: =E24/E25 -> 0.2641931 | F26: =F24/F25 -> 0.24224007 | G26: =G24/G25 -> 0.2549947 | H26: =MEDIAN(C26:G26) -> 0.2641931 | I26: =H26 -> 0.2641931 | J26: =I26 -> 0.2641931 | K26: =J26 -> 0.2641931 | L26: =K26 -> 0.2641931

Sheet bs drivers
B2: Balance Sheet Drivers
B3: All the Figures In Crores
B4: Financial Year | C4: 44389 | D4: =C4+365 -> 44754 | E4: =D4+365 -> 45119 | F4: =E4+365 -> 45484 | G4: =F4+365 -> 45849 | H4: =G4+365 -> 46214 | I4: =H4+365 -> 46579 | J4: =I4+365 -> 46944 | K4: =J4+365 -> 47309 | L4: =K4+365 -> 47674
B5: Current Assets
B6: Inventories | C6: ='balance sheet1'!C7 -> 5820.54 | D6: ='balance sheet1'!D7 -> 5943.32 | E6: ='balance sheet1'!E7 -> 6828.78 | F6: ='balance sheet1'!F7 -> 6620.19 | G6: ='balance sheet1'!G7 -> 7670.55 | H6: =H7*H8 -> 11408.643 | I6: =I7*I8 -> 12918.469 | J6: =J7*J8 -> 14471.988 | K6: =K7*K8 -> 15981.212 | L6: =L7*L8 -> 17348.487
B7: COGS | C7: ='income statement'!C9 -> 79009.86 | D7: ='income statement'!D9 -> 93785.97 | E7: ='income statement'!E9 -> 110588.83 | F7: ='income statement'!F9 -> 140313.92 | G7: ='income statement'!G9 -> 164670.67 | H7: ='income statement'!H9 -> 184757.52 | I7: ='income statement'!I9 -> 209208.44 | J7: ='income statement'!J9 -> 234366.93 | ... L7: ='income statement'!L9 -> 280950.46
B8: Inventories (as a % of COGS) | C8: =C6/C7 -> 0.073668527 | D8: =D6/D7 -> 0.063371099 | E8: =E6/E7 -> 0.061749274 | F8: =F6/F7 -> 0.047181278 | G8: =G6/G7 -> 0.046581155 | H8: =MEDIAN(C8:G8) -> 0.061749274 | I8: =MEDIAN(D8:H8) -> 0.061749274 | J8: =MEDIAN(E8:I8) -> 0.061749274 | K8: =MEDIAN(F8:J8) -> 0.061749274 | L8: =MEDIAN(G8:K8) -> 0.061749274
B10: Investments | C10: ='balance sheet1'!C8 -> 31011.23 | D10: ='balance sheet1'!D8 -> 29799.58 | E10: ='balance sheet1'!E8 -> 35573.42 | F10: ='balance sheet1'!F8 -> 34957.63 | G10: ='balance sheet1'!G8 -> 43360.62 | H10: =H11*H12 -> 54078.47 | I10: =I11*I12 -> 60643.548 | J10: =J11*J12 -> 67531.067 | K10: =K11*K12 -> 74133.82 | L10: =L11*L12 -> 80677.093
B11: Revenue | C11: ='income statement'!C6 -> 135979.03 | D11: ='income statement'!D6 -> 156521.23 | E11: ='income statement'!E6 -> 183340.7 | F11: ='income statement'!F6 -> 221112.91 | G11: ='income statement'!G6 -> 255734.45 | H11: ='income statement'!H6 -> 287612.69 | I11: ='income statement'!I6 -> 322528.62 | J11: ='income statement'!J6 -> 359159.42 | ... L11: ='income statement'!L6 -> 429075.67
B12: Investments (as a % of Revenue) | C12: =C10/C11 -> 0.22805891 | D12: =D10/D11 -> 0.19038682 | E12: =E10/E11 -> 0.19402904 | F12: =F10/F11 -> 0.15809855 | G12: =G10/G11 -> 0.1695533 | H12: =AVERAGE($C$12:$G$12) -> 0.18802533 | I12: =AVERAGE($C$12:$G$12) -> 0.18802533 | J12: =AVERAGE($C$12:$G$12) -> 0.18802533 | K12: =AVERAGE($C$12:$G$12) -> 0.18802533 | L12: =AVERAGE($C$12:$G$12) -> 0.18802533
B14: Trade receivables | C14: ='balance sheet1'!C9 -> 42229.78 | D14: ='balance sheet1'!D9 -> 46139.32 | E14: ='balance sheet1'!E9 -> 44731.53 | F14: ='balance sheet1'!F9 -> 48770.95 | G14: ='balance sheet1'!G9 -> 53713.68 | H14: =H15*H16 -> 73624.739 | I14: =I15*I16 -> 82562.718 | J14: =J15*J16 -> 91939.68 | K14: =K15*K16 -> 100928.95 | L14: =L15*L16 -> 109837.24
B15: Revenue | C15: =C11 -> 135979.03 | D15: =D11 -> 156521.23 | E15: =E11 -> 183340.7 | F15: =F11 -> 221112.91 | G15: =G11 -> 255734.45 | H15: =H11 -> 287612.69 | I15: =I11 -> 322528.62 | J15: =J11 -> 359159.42 | ... L15: =L11 -> 429075.67
B16: Trade Receivables (as a % of Revenue) | C16: =C14/C15 -> 0.31056097 | D16: =D14/D15 -> 0.29477995 | E16: =E14/E15 -> 0.24398036 | F16: =F14/F15 -> 0.22057034 | G16: =G14/G15 -> 0.21003693 | H16: =AVERAGE($C$16:$G$16) -> 0.25598571 | I16: =AVERAGE($C$16:$G$16) -> 0.25598571 | J16: =AVERAGE($C$16:$G$16) -> 0.25598571 | K16: =AVERAGE($C$16:$G$16) -> 0.25598571 | L16: =AVERAGE($C$16:$G$16) -> 0.25598571
B18: Other bank balances | C18: ='balance sheet1'!C11 -> 2867.98 | D18: ='balance sheet1'!D11 -> 5182.93 | E18: ='balance sheet1'!E11 -> 5592.91 | F18: ='balance sheet1'!F11 -> 3399.89 | G18: ='balance sheet1'!G11 -> 10778.34 | H18: =H19*H20 -> 8181.6054 | I18: =I19*I20 -> 9174.8451 | J18: =J19*J20 -> 10216.867 | K18: =K19*K20 -> 11215.807 | L18: =L19*L20 -> 12205.747
B19: Revenue | C19: =C15 -> 135979.03 | D19: =D15 -> 156521.23 | E19: =E15 -> 183340.7 | F19: =F15 -> 221112.91 | G19: =G15 -> 255734.45 | H19: =H15 -> 287612.69 | I19: =I15 -> 322528.62 | J19: =J15 -> 359159.42 | ... L19: =L15 -> 429075.67
B20: Other Bank Balances (As a % of Revenue) | C20: =C18/C19 -> 0.02109134 | D20: =D18/D19 -> 0.033113272 | E20: =E18/E19 -> 0.030505556 | F20: =F18/F19 -> 0.015376262 | G20: =G18/G19 -> 0.04214661 | H20: =AVERAGE($C$20:$G$20) -> 0.028446608 | I20: =AVERAGE($C$20:$G$20) -> 0.028446608 | J20: =AVERAGE($C$20:$G$20) -> 0.028446608 | K20: =AVERAGE($C$20:$G$20) -> 0.028446608 | L20: =AVERAGE($C$20:$G$20) -> 0.028446608
B22: Loans towards financing activities | C22: ='balance sheet1'!C12 -> 41379.03 | D22: ='balance sheet1'!D12 -> 42269.2 | E22: ='balance sheet1'!E12 -> 40460.55 | F22: ='balance sheet1'!F12 -> 34814.59 | G22: ='balance sheet1'!G12 -> 36077.51 | H22: =G22 -> 36077.51 | I22: =H22 -> 36077.51 | J22: =I22 -> 36077.51 | K22: =J22 -> 36077.51 | L22: =K22 -> 36077.51
B24: Other loans | C24: ='balance sheet1'!C13 -> 235.35 | D24: ='balance sheet1'!D13 -> 280.34 | E24: ='balance sheet1'!E13 -> 251.15 | F24: ='balance sheet1'!F13 -> 106.54 | G24: ='balance sheet1'!G13 -> 416.85 | H24: =G24 -> 416.85 | I24: =H24 -> 416.85 | J24: =I24 -> 416.85 | K24: =J24 -> 416.85 | L24: =K24 -> 416.85
B26: Other financial assets | C26: ='balance sheet1'!C14 -> 3251.68 | D26: ='balance sheet1'!D14 -> 3655.82 | E26: ='balance sheet1'!E14 -> 4930.1 | F26: ='balance sheet1'!F14 -> 5563.92 | G26: ='balance sheet1'!G14 -> 5419.89 | H26: =G26 -> 5419.89 | I26: =H26 -> 5419.89 | J26: =I26 -> 5419.89 | K26: =J26 -> 5419.89 | L26: =K26 -> 5419.89
B28: Other current assets | C28: ='balance sheet1'!C15 -> 54791.48 | D28: ='balance sheet1'!D15 -> 60331.55 | E28: ='balance sheet1'!E15 -> 65920.39 | F28: ='balance sheet1'!F15 -> 71391.03 | G28: ='balance sheet1'!G15 -> 75559.83 | H28: =G28 -> 75559.83 | I28: =H28 -> 75559.83 | J28: =I28 -> 75559.83 | K28: =J28 -> 75559.83 | L28: =K28 -> 75559.83
B30: Non-Current Assets
B31: Property, plant & equipment | H31: 0.0552 | I31: 0.0563 | J31: 0.0573 | K31: 0.0583 | L31: 0.059
B32: Investment property | H32: 0 | I32: 0 | J32: 0 | K32: 0 | L32: 0
B33: Other intangible assets | H33: 0 | I33: 0 | J33: 0 | K33: 0 | L33: 0
B34: Right-of-use assets | H34: 0.0619 | I34: 0.0612 | J34: 0.0608 | K34: 0.0603 | L34: 0.0599
B35: Capital work-in-progress | H35: 0.2506 | I35: 0.2507 | J35: 0.2508 | K35: 0.2509 | L35: 0.2511
B36: Investment property under construction | H36: 0 | I36: 0 | J36: 0 | K36: 0 | L36: 0
B37: Goodwill | H37: =I60 -> 0 | I37: =J60 -> 0 | J37: =K60 -> 0 | K37: =L60 -> 0 | L37: =M60 -> 0
B38: Intangible assets under development | H38: 0.1481 | I38: 0.1623 | J38: 0.1634 | K38: 0.1631 | L38: 0.1613
B39: Investments in joint ventures & associa | H39: 0 | I39: 0 | J39: 0 | K39: 0 | L39: 0
B40: Other investments | H40: 0.1131 | I40: 0.1131 | J40: 0.1131 | K40: 0.1131 | L40: 0.1131
B41: Loans towards financing activities | H41: 0.0453 | I41: 0.0453 | J41: 0.0453 | K41: 0.0453 | L41: 0.0453
B42: Other loans | H42: 0.1913 | I42: 0.1913 | J42: 0.1913 | K42: 0.1913 | L42: 0.1913
B43: Other financial assets | H43: 0.0702 | I43: 0.0702 | J43: 0.0702 | K43: 0.0702 | L43: 0.0702
B44: Deferred tax assets (net) | H44: 0.089 | I44: 0.089 | J44: 0.089 | K44: 0.089 | L44: 0.089
B45: Current Tax Assets (net) | H45: 0.1265 | I45: 0.1265 | J45: 0.1265 | K45: 0.1265 | L45: 0.1265
B46: Other non-current assets | H46: 0 | I46: 0 | J46: 0 | K46: 0 | L46: 0
B52: Property, Plant & Equipment | H52: =G58 -> 14128.56 | I52: =H58 -> 14043.766 | J52: =I58 -> 13974.033 | K52: =J58 -> 13932.585 | L52: =K58 -> 13904.398
B53: Capex Growth Rate | H53: =H31 -> 0.0552 | I53: =I31 -> 0.0563 | J53: =J31 -> 0.0573 | K53: =K31 -> 0.0583 | L53: =L31 -> 0.059
B54: Capex | H54: =H52*H53 -> 779.89651 | I54: =I52*I53 -> 790.66403 | J54: =J52*J53 -> 800.7121 | K54: =K52*K53 -> 812.26969 | L54: =L52*L53 -> 820.35947
B55: Gross Block | H55: =H52+H54 -> 14908.457 | I55: =I52+I54 -> 14834.43 | J55: =J52+J54 -> 14774.745 | K55: =K52+K54 -> 14744.854 | L55: =L52+L54 -> 14724.757
B56: Rate of Depreciation | H56: 0.058 | I56: 0.058 | J56: 0.057 | K56: 0.057 | L56: 0.056
B57: Amount of Depreciation | H57: =H55*H56 -> 864.69048 | I57: =I55*I56 -> 860.39694 | J57: =J55*J56 -> 842.16048 | K57: =K55*K56 -> 840.4567 | L57: =L55*L56 -> 824.5864
B58: Net Block | C58: ='balance sheet1'!C23 -> 11386.29 | D58: ='balance sheet1'!D23 -> 10577.98 | E58: ='balance sheet1'!E23 -> 11336.28 | F58: ='balance sheet1'!F23 -> 13297.64 | G58: ='balance sheet1'!G23 -> 14128.56 | H58: =H55-H57 -> 14043.766 | I58: =I55-I57 -> 13974.033 | J58: =J55-J57 -> 13932.585 | K58: =K55-K57 -> 13904.398 | L58: =L55-L57 -> 13900.171
B61: Capital Work-in-Progress (CWIP) | H61: =G67 -> 2390.86 | I61: =H67 -> 2990.0095 | J61: =I67 -> 3739.6049 | K61: =J67 -> 4677.4978 | L61: =K67 -> 5851.082
B62: Capex Growth Rate | H62: =H35 -> 0.2506 | I62: =I35 -> 0.2507 | J62: =J35 -> 0.2508 | K62: =K35 -> 0.2509 | L62: =L35 -> 0.2511
B63: Capex | H63: =H61*H62 -> 599.14952 | I63: =I61*I62 -> 749.59539 | J63: =J61*J62 -> 937.89291 | K63: =K61*K62 -> 1173.5842 | L63: =L61*L62 -> 1469.2067
B64: Gross Block | H64: =H61+H63 -> 2990.0095 | I64: =I61+I63 -> 3739.6049 | J64: =J61+J63 -> 4677.4978 | K64: =K61+K63 -> 5851.082 | L64: =L61+L63 -> 7320.2887
B65: Rate of Depreciation | H65: 0 | I65: 0 | J65: 0 | K65: 0 | L65: 0
B66: Amount of Depreciation | H66: =H64*H65 -> 0 | I66: =I64*I65 -> 0 | J66: =J64*J65 -> 0 | K66: =K64*K65 -> 0 | L66: =L64*L65 -> 0
B67: Net Block | C67: 388.37 | D67: 1170.32 | E67: 2949.09 | F67: 2897.04 | G67: 2390.86 | H67: =H64-H66 -> 2990.0095 | I67: =I64-I66 -> 3739.6049 | J67: =J64-J66 -> 4677.4978 | K67: =K64-K66 -> 5851.082 | L67: =L64-L66 -> 7320.2887
B69: Investment Property | H69: =G75 -> 1157.33 | I69: =H75 -> 1099.4635 | J69: =I75 -> 1044.4903 | K69: =J75 -> 992.26581 | L69: =K75 -> 942.65252
B70: Capex Growth Rate | H70: =H33 -> 0 | I70: =I33 -> 0 | J70: =J33 -> 0 | K70: =K33 -> 0 | L70: =L33 -> 0
B71: Capex | H71: =H69*(H70) -> 0 | I71: =I69*(I70) -> 0 | J71: =J69*(J70) -> 0 | K71: =K69*(K70) -> 0 | L71: =L69*(L70) -> 0
B72: Gross Block | H72: =H69-H71 -> 1157.33 | I72: =I69+I71 -> 1099.4635 | J72: =J69+J71 -> 1044.4903 | K72: =K69+K71 -> 992.26581 | L72: =L69+L71 -> 942.65252
B73: Rate of Depreciation | H73: 0.05 | I73: 0.05 | J73: 0.05 | K73: 0.05 | L73: 0.05
B74: Amount of Depreciation | H74: =H72*H73 -> 57.8665 | I74: =I72*I73 -> 54.973175 | J74: =J72*J73 -> 52.224516 | K74: =K72*K73 -> 49.61329 | L74: =L72*L73 -> 47.132626
B75: Net Block | C75: 3646.78 | D75: 3962.98 | E75: 3360.22 | F75: 1936.44 | G75: 1157.33 | H75: =H72-H74 -> 1099.4635 | I75: =I72-I74 -> 1044.4903 | J75: =J72-J74 -> 992.26581 | K75: =K72-K74 -> 942.65252 | L75: =L72-L74 -> 895.51989
B77: Goodwill | H77: =G83 -> 8348.48 | I77: =H83 -> 8348.48 | J77: =I83 -> 8348.48 | K77: =J83 -> 8348.48 | L77: =K83 -> 8348.48
B78: Capex Growth Rate | H78: =H37 -> 0 | I78: =I37 -> 0 | J78: =J37 -> 0 | K78: =K37 -> 0 | L78: =L37 -> 0
B79: Capex | H79: =H77*H78 -> 0 | I79: =I77*I78 -> 0 | J79: =J77*J78 -> 0 | K79: =K77*K78 -> 0 | L79: =L77*L78 -> 0
B80: Gross Block | H80: =H77+H79 -> 8348.48 | I80: =I77+I79 -> 8348.48 | J80: =J77+J79 -> 8348.48 | K80: =K77+K79 -> 8348.48 | L80: =L77+L79 -> 8348.48
B81: Rate of Depreciation | H81: 0 | I81: 0 | J81: 0 | K81: 0 | L81: 0
B82: Amount of Depreciation | H82: =H80*H81 -> 0 | I82: =I80*I81 -> 0 | J82: =J80*J81 -> 0 | K82: =K80*K81 -> 0 | L82: =L80*L81 -> 0
B83: Net Block | C83: 8066.96 | D83: 7685.17 | E83: 7798.65 | F83: 7800.88 | G83: 8348.48 | H83: =H80-H82 -> 8348.48 | I83: =I80-I82 -> 8348.48 | J83: =J80-J82 -> 8348.48 | K83: =K80-K82 -> 8348.48 | L83: =L80-L82 -> 8348.48
B85: Other Intangible Assets | H85: =G91 -> 17050.76 | I85: =H91 -> 17050.76 | J85: =I91 -> 17050.76 | K85: =J91 -> 17050.76 | L85: =K91 -> 17050.76
B86: Capex Growth Rate | H86: =H36 -> 0 | I86: =I36 -> 0 | J86: =J36 -> 0 | K86: =K36 -> 0 | L86: =L36 -> 0
B87: Capex | H87: =H85*H86 -> 0 | I87: =I85*I86 -> 0 | J87: =J85*J86 -> 0 | K87: =K85*K86 -> 0 | L87: =L85*L86 -> 0
B88: Gross Block | H88: =H85+H87 -> 17050.76 | I88: =I85+I87 -> 17050.76 | J88: =J85+J87 -> 17050.76 | K88: =K85+K87 -> 17050.76 | L88: =L85+L87 -> 17050.76
B89: Rate of Depreciation | H89: =H33 -> 0 | I89: =I33 -> 0 | J89: =J33 -> 0 | K89: =K33 -> 0 | L89: =L33 -> 0
B90: Amount of Depreciation | H90: =H88*H89 -> 0 | I90: =I88*I89 -> 0 | J90: =J88*J89 -> 0 | K90: =K88*K89 -> 0 | L90: =L88*L89 -> 0
B91: Net Block | C91: 19197.76 | D91: 18729.37 | E91: 18007.98 | F91: 17384.52 | G91: 17050.76 | H91: =H88-H90 -> 17050.76 | I91: =I88-I90 -> 17050.76 | J91: =J88-J90 -> 17050.76 | K91: =K88-K90 -> 17050.76 | L91: =L88-L90 -> 17050.76
B93: Right-of-Use Assets | H93: =G99 -> 2869.02 | I93: =H99 -> 2858.027 | J93: =I99 -> 2847.3225 | K93: =J99 -> 2836.7969 | L93: =K99 -> 2826.4821
B94: Capex Growth Rate | H94: =H34 -> 0.0619 | I94: =I34 -> 0.0612 | J94: =J34 -> 0.0608 | K94: =K34 -> 0.0603 | L94: =L34 -> 0.0599
B95: Capex | H95: =H93*H94 -> 177.59234 | I95: =I93*I94 -> 174.91125 | J95: =J93*J94 -> 173.11721 | K95: =K93*K94 -> 171.05886 | L95: =L93*L94 -> 169.30628
B96: Gross Block | H96: =H93+H95 -> 3046.6123 | I96: =I93+I95 -> 3032.9383 | J96: =J93+J95 -> 3020.4397 | K96: =K93+K95 -> 3007.8558 | L96: =L93+L95 -> 2995.7884
B97: Rate of Depreciation | H97: =H34 -> 0.0619 | I97: =I34 -> 0.0612 | J97: =J34 -> 0.0608 | K97: =K34 -> 0.0603 | L97: =L34 -> 0.0599
B98: Amount of Depreciation | H98: =H96*H97 -> 188.5853 | I98: =I96*I97 -> 185.61582 | J98: =J96*J97 -> 183.64273 | K98: =K96*K97 -> 181.3737 | L98: =L96*L97 -> 179.44772
B99: Net Block | C99: 2021.53 | D99: 1989.51 | E99: 2137.87 | F99: 2289.41 | G99: 2869.02 | H99: =H96-H98 -> 2858.027 | I99: =I96-I98 -> 2847.3225 | J99: =J96-J98 -> 2836.7969 | K99: =K96-K98 -> 2826.4821 | L99: =L96-L98 -> 2816.3406
B101: Investments in JVs & Associates | H101: =G107 -> 2318.42 | I101: =H107 -> 2318.42 | J101: =I107 -> 2318.42 | K101: =J107 -> 2318.42 | L101: =K107 -> 2318.42
B102: Capex Growth Rate | H102: =H39 -> 0 | I102: =I39 -> 0 | J102: =J39 -> 0 | K102: =K39 -> 0 | L102: =L39 -> 0
B103: Capex | H103: =H101*H102 -> 0 | I103: =I101*I102 -> 0 | J103: =J101*J102 -> 0 | K103: =K101*K102 -> 0 | L103: =L101*L102 -> 0
B104: Gross Block | H104: =H101+H103 -> 2318.42 | I104: =I101+I103 -> 2318.42 | J104: =J101+J103 -> 2318.42 | K104: =K101+K103 -> 2318.42 | L104: =L101+L103 -> 2318.42
B105: Rate of Depreciation | H105: 0 | I105: 0 | J105: 0 | K105: 0 | L105: 0
B106: Amount of Depreciation | H106: =H104*H105 -> 0 | I106: =I104*I105 -> 0 | J106: =J104*J105 -> 0 | K106: =K104*K105 -> 0 | L106: =L104*L105 -> 0
B107: Net Block | C107: 2670.26 | D107: 2521.16 | E107: 1304.86 | F107: 1264.25 | G107: 2318.42 | H107: =H104-H106 -> 2318.42 | I107: =I104-I106 -> 2318.42 | J107: =J104-J106 -> 2318.42 | K107: =K104-K106 -> 2318.42 | L107: =L104-L106 -> 2318.42
B109: Other Investments | H109: =G115 -> 9126.23 | I109: =H115 -> 10158.407 | J109: =I115 -> 11307.322 | K109: =J115 -> 12586.181 | L109: =K115 -> 14009.678
B110: Capex Growth Rate | H110: =H40 -> 0.1131 | I110: =I40 -> 0.1131 | J110: =J40 -> 0.1131 | K110: =K40 -> 0.1131 | L110: =L40 -> 0.1131
B111: Capex | H111: =H109*H110 -> 1032.1766 | I111: =I109*I110 -> 1148.9158 | J111: =J109*J110 -> 1278.8582 | K111: =K109*K110 -> 1423.497 | L111: =L109*L110 -> 1584.4945
B112: Gross Block | H112: =H109+H111 -> 10158.407 | I112: =I109+I111 -> 11307.322 | J112: =J109+J111 -> 12586.181 | K112: =K109+K111 -> 14009.678 | L112: =L109+L111 -> 15594.172
B113: Rate of Depreciation | H113: 0 | I113: 0 | J113: 0 | K113: 0 | L113: 0
B114: Amount of Depreciation | H114: =H112*H113 -> 0 | I114: =I112*I113 -> 0 | J114: =J112*J113 -> 0 | K114: =K112*K113 -> 0 | L114: =L112*L113 -> 0
B115: Net Block | C115: 5945.14 | D115: 7074.44 | E115: 7920.03 | F115: 9425.94 | G115: 9126.23 | H115: =H112-H114 -> 10158.407 | I115: =I112-I114 -> 11307.322 | J115: =J112-J114 -> 12586.181 | K115: =K112-K114 -> 14009.678 | L115: =L112-L114 -> 15594.172
B117: Loans towards Financing Activities (Financial Services) | H117: =G123 -> 62847.35 | I117: =H123 -> 65694.335 | J117: =I123 -> 68670.288 | K117: =J123 -> 71781.052 | L117: =K123 -> 75032.734
B118: Capex Growth Rate | H118: =H41 -> 0.0453 | I118: =I41 -> 0.0453 | J118: =J41 -> 0.0453 | K118: =K41 -> 0.0453 | L118: =L41 -> 0.0453
B119: Capex | H119: =H117*H118 -> 2846.985 | I119: =I117*I118 -> 2975.9534 | J119: =J117*J118 -> 3110.7641 | K119: =K117*K118 -> 3251.6817 | L119: =L117*L118 -> 3398.9829
B120: Gross Block | H120: =H117+H119 -> 65694.335 | I120: =I117+I119 -> 68670.288 | J120: =J117+J119 -> 71781.052 | K120: =K117+K119 -> 75032.734 | L120: =L117+L119 -> 78431.717
B121: Rate of Depreciation | H121: 0 | I121: 0 | J121: 0 | K121: 0 | L121: 0
B122: Amount of Depreciation | H122: =H120*H121 -> 0 | I122: =I120*I121 -> 0 | J122: =J120*J121 -> 0 | K122: =K120*K121 -> 0 | L122: =L120*L121 -> 0
B123: Net Block | C123: 52631.67 | D123: 46736.84 | E123: 40920.92 | F123: 52154.76 | G123: 62847.35 | H123: =H120-H122 -> 65694.335 | I123: =I120-I122 -> 68670.288 | J123: =J120-J122 -> 71781.052 | K123: =K120-K122 -> 75032.734 | L123: =L120-L122 -> 78431.717
...

Sheet forcast
D4: Sr.no | E4: Years | F4: Revenue | G4: growth | Q4: regration - function
D5: 1 | E5: 42460 | F5: 101975 | G5: 0 | P5: S.no | Q5: Years | R5: Sales
D6: 2 | E6: 42825 | F6: 110011 | G6: =F6/F5-1 -> 0.078803628 | P6: =1 -> 1 | Q6: 42460 | R6: 101975 | S6: 0
D7: 3 | E7: 43190 | F7: 119862 | G7: =F7/F6-1 -> 0.089545591 | P7: =P6+1 -> 2 | Q7: 42825 | R7: 110011 | S7: =R7/R6-1 -> 0.078803628
D8: 4 | E8: 43555 | F8: 135220 | G8: =F8/F7-1 -> 0.12813068 | P8: =P7+1 -> 3 | Q8: 43190 | R8: 119862 | S8: =R8/R7-1 -> 0.089545591
D9: 5 | E9: 43921 | F9: 145452 | G9: =F9/F8-1 -> 0.07566928 | P9: =P8+1 -> 4 | Q9: 43555 | R9: 135220 | S9: =R9/R8-1 -> 0.12813068
D10: 6 | E10: 44286 | F10: 135979 | G10: =F10/F9-1 -> -0.065128015 | L10: CAGR | P10: =P9+1 -> 5 | Q10: 43921 | R10: 145452 | S10: =R10/R9-1 -> 0.07566928
D11: 7 | E11: 44651 | F11: 156521 | G11: =F11/F10-1 -> 0.15106744 | K11: S.no | L11: Years | M11: Sales | P11: =P10+1 -> 6 | Q11: 44286 | R11: 135979 | S11: =R11/R10-1 -> -0.065128015
D12: 8 | E12: 45016 | F12: 183341 | G12: =F12/F11-1 -> 0.17135081 | K12: =1 -> 1 | L12: 42460 | M12: 101975 | P12: =P11+1 -> 7 | Q12: 44651 | R12: 156521 | S12: =R12/R11-1 -> 0.15106744
D13: 9 | E13: 45382 | F13: 221113 | G13: =F13/F12-1 -> 0.20602048 | K13: =K12+1 -> 2 | L13: 42825 | M13: 110011 | P13: =P12+1 -> 8 | Q13: 45016 | R13: 183341 | S13: =R13/R12-1 -> 0.17135081
D14: 10 | E14: 45747 | F14: 255734 | G14: =F14/F13-1 -> 0.15657605 | K14: =K13+1 -> 3 | L14: 43190 | M14: 119862 | P14: =P13+1 -> 9 | Q14: 45382 | R14: 221113 | S14: =R14/R13-1 -> 0.20602048
D15: 11 | E15: 46112 | F15: =F14*(1+G15) -> 299529.39 | G15: =AVERAGE(G11:G14) -> 0.17125369 | K15: =K14+1 -> 4 | L15: 43555 | M15: 135220 | P15: =P14+1 -> 10 | Q15: 45747 | R15: 255734 | S15: =R15/R14-1 -> 0.15657605
D16: 12 | E16: 46477 | F16: =F15*(1+G16) -> 352336.5 | G16: =AVERAGE(G12:G15) -> 0.17630026 | K16: =K15+1 -> 5 | L16: 43921 | M16: 145452 | P16: =P15+1 -> 11 | Q16: 46112 | R16: =_xlfn.FORECAST.LINEAR(P16,R6:R15,P6:P15) -> 240966.47 | S16: =R16/R15-1 -> -0.057745678
D17: 13 | E17: 46843 | F17: =F16*(1+G17) -> 414889.48 | G17: =AVERAGE(G13:G16) -> 0.17753762 | K17: =K16+1 -> 6 | L17: 44286 | M17: 135979 | N17: pv | P17: =P16+1 -> 12 | Q17: 46477 | R17: =_xlfn.FORECAST.LINEAR(P17,R7:R16,P7:P16) -> 260199.19 | S17: =R17/R16-1 -> 0.079814923
D18: 14 | E18: 47208 | F18: =F17*(1+G18) -> 485593.67 | G18: =AVERAGE(G14:G17) -> 0.17041691 | K18: =K17+1 -> 7 | L18: 44651 | M18: 156521 | P18: =P17+1 -> 13 | Q18: 46843 | R18: =_xlfn.FORECAST.LINEAR(P18,R8:R17,P8:P17) -> 280001.83 | S18: =R18/R17-1 -> 0.076105709
D19: 15 | E19: 47573 | F19: =F18*(1+G19) -> 570027.29 | G19: =AVERAGE(G15:G18) -> 0.17387712 | K19: =K18+1 -> 8 | L19: 45016 | M19: 183341 | P19: =P18+1 -> 14 | Q19: 47208 | R19: =_xlfn.FORECAST.LINEAR(P19,R9:R18,P9:P18) -> 300339.92 | S19: =R19/R18-1 -> 0.072635556
K20: =K19+1 -> 9 | L20: 45382 | M20: 221113 | P20: =P19+1 -> 15 | Q20: 47573 | R20: =_xlfn.FORECAST.LINEAR(P20,R10:R19,P10:P19) -> 322232.72 | S20: =R20/R19-1 -> 0.072893414
K21: =K20+1 -> 10 | L21: 45747 | M21: 255734 | N21: fv
K22: =K21+1 -> 11 | L22: 46112 | M22: =M21*(1+N22) -> 290169.52 | N22: =_xlfn.RRI(5,M17,M21) -> 0.13465368
K23: =K22+1 -> 12 | L23: 46477 | M23: =M22*(1+N23) -> 328297.54 | N23: =_xlfn.RRI(5,M18,M22) -> 0.13139912
K24: =K23+1 -> 13 | L24: 46843 | M24: =M23*(1+N24) -> 368866.52 | N24: =_xlfn.RRI(5,M19,M23) -> 0.12357381
K25: =K24+1 -> 14 | L25: 47208 | M25: =M24*(1+N25) -> 408620.58 | N25: =_xlfn.RRI(5,M20,M24) -> 0.10777355
K26: =K25+1 -> 15 | L26: 47573 | M26: =M25*(1+N26) -> 448772.86 | N26: =_xlfn.RRI(5,M21,M25) -> 0.098263

Sheet 3 statement model->

Sheet income statement
L2: Index!A1
B3: Income Statement
B4: All the Figures In Crores
B5: Financial Year | C5: 44389 | D5: =C5+365 -> 44754 | E5: =D5+365 -> 45119 | F5: =E5+365 -> 45484 | G5: =F5+365 -> 45849 | H5: =G5+365 -> 46214 | I5: =H5+365 -> 46579 | J5: =I5+365 -> 46944 | K5: =J5+365 -> 47309 | L5: =K5+365 -> 47674
B6: Revenue from operations | C6: ='p&l'!C5 -> 135979.03 | D6: ='p&l'!D5 -> 156521.23 | E6: ='p&l'!E5 -> 183340.7 | F6: ='p&l'!F5 -> 221112.91 | G6: ='p&l'!G5 -> 255734.45 | H6: =G6*(1+'p&L drivers'!H7) -> 287612.69 | I6: =H6*(1+'p&L drivers'!I7) -> 322528.62 | J6: =I6*(1+'p&L drivers'!J7) -> 359159.42 | K6: =J6*(1+'p&L drivers'!K7) -> 394275.71 | L6: =K6*(1+'p&L drivers'!L7) -> 429075.67
B7: Other income net | C7: ='p&l'!C6 -> 3429.35 | D7: ='p&l'!D6 -> 2267.08 | E7: ='p&l'!E6 -> 2929.17 | F7: ='p&l'!F6 -> 4158.03 | G7: ='p&l'!G6 -> 4124.82 | H7: =G7 -> 4124.82 | I7: =H7 -> 4124.82 | J7: =I7 -> 4124.82 | K7: =J7 -> 4124.82 | L7: =K7 -> 4124.82
B8: Total Income | C8: =SUM(C6:C7) -> 139408.38 | D8: =SUM(D6:D7) -> 158788.31 | E8: =SUM(E6:E7) -> 186269.87 | F8: =SUM(F6:F7) -> 225270.94 | G8: =SUM(G6:G7) -> 259859.27 | H8: =SUM(H6:H7) -> 291737.51 | I8: =SUM(I6:I7) -> 326653.44 | J8: =SUM(J6:J7) -> 363284.24 | ... L8: =SUM(L6:L7) -> 433200.49
B9: COGS | C9: =SUM('p&l'!C9:C15) -> 79009.86 | D9: =SUM('p&l'!D9:D15) -> 93785.97 | E9: =SUM('p&l'!E9:E15) -> 110588.83 | F9: =SUM('p&l'!F9:F15) -> 140313.92 | G9: =SUM('p&l'!G9:G15) -> 164670.67 | H9: =H6*'p&L drivers'!H13 -> 184757.52 | I9: =I6*'p&L drivers'!I13 -> 209208.44 | J9: =J6*'p&L drivers'!J13 -> 234366.93 | K9: =K6*'p&L drivers'!K13 -> 258808.09 | L9: =L6*'p&L drivers'!L13 -> 280950.46
B10: Gross Profit | C10: =C8-C9 -> 60398.52 | D10: =D8-D9 -> 65002.34 | E10: =E8-E9 -> 75681.04 | F10: =F8-F9 -> 84957.02 | G10: =G8-G9 -> 95188.6 | H10: =H8-H9 -> 106979.99 | I10: =I8-I9 -> 117445 | J10: =J8-J9 -> 128917.31 | ... L10: =L8-L9 -> 152250.03
B11: Employee benefits expense | C11: ='p&l'!C18 -> 24750.54 | D11: ='p&l'!D18 -> 29733.53 | E11: ='p&l'!E18 -> 37214.11 | F11: ='p&l'!F18 -> 41171.02 | G11: ='p&l'!G18 -> 46768.68 | H11: =G11*(1+'p&L drivers'!H19) -> 54897.138 | I11: =H11*(1+'p&L drivers'!I19) -> 64438.333 | J11: =I11*(1+'p&L drivers'!J19) -> 75637.8 | K11: =J11*(1+'p&L drivers'!K19) -> 88783.75 | L11: =K11*(1+'p&L drivers'!L19) -> 104214.48
B12: Finance cost of financial services business and finance lease activity | C12: ='p&l'!C16 -> 7691.04 | D12: ='p&l'!D16 -> 5952.54 | E12: ='p&l'!E16 -> 6026.44 | F12: ='p&l'!F16 -> 5714.9 | G12: ='p&l'!G16 -> 6302.23 | H12: ='p&L drivers'!H22 -> 6302.23 | I12: ='p&L drivers'!I22 -> 6302.23 | J12: ='p&L drivers'!J22 -> 6302.23 | K12: ='p&L drivers'!K22 -> 6302.23 | L12: ='p&L drivers'!L22 -> 6302.23
B13: Sales, administration and other expenses | C13: ='p&l'!C19 -> 8903.49 | D13: ='p&l'!D19 -> 8831.89 | E13: ='p&l'!E19 -> 8758.04 | F13: ='p&l'!F19 -> 10419.42 | G13: ='p&l'!G19 -> 11558.13 | H13: =G13*(1+'p&L drivers'!H20) -> 12821.287 | I13: =H13*(1+'p&L drivers'!I20) -> 14222.49 | J13: =I13*(1+'p&L drivers'!J20) -> 15776.827 | K13: =J13*(1+'p&L drivers'!K20) -> 17501.034 | L13: =K13*(1+'p&L drivers'!L20) -> 19413.674
B14: Total Expense | C14: =SUM(C11:C13) -> 41345.07 | D14: =SUM(D11:D13) -> 44517.96 | E14: =SUM(E11:E13) -> 51998.59 | F14: =SUM(F11:F13) -> 57305.34 | G14: =SUM(G11:G13) -> 64629.04 | H14: =SUM(H11:H13) -> 74020.655 | I14: =SUM(I11:I13) -> 84963.053 | J14: =SUM(J11:J13) -> 97716.858 | ... L14: =SUM(L11:L13) -> 129930.39
B15: EBITDA | C15: =C10-C14 -> 19053.45 | D15: =D10-D14 -> 20484.38 | E15: =E10-E14 -> 23682.45 | F15: =F10-F14 -> 27651.68 | G15: =G10-G14 -> 30559.56 | H15: =H10-H14 -> 32959.339 | I15: =I10-I14 -> 32481.949 | J15: =J10-J14 -> 31200.452 | ... L15: =L10-L14 -> 22319.642
B16: Depreciation, amortisation, impairment and obsolescence | C16: ='p&l'!C21 -> 2904.21 | D16: ='p&l'!D21 -> 2947.95 | E16: ='p&l'!E21 -> 3502.25 | F16: ='p&l'!F21 -> 3682.33 | G16: ='p&l'!G21 -> 4121.18 | H16: ='bs drivers'!H186 -> 1111.1423 | I16: ='bs drivers'!I186 -> 1100.9859 | J16: ='bs drivers'!J186 -> 1078.0277 | K16: ='bs drivers'!K186 -> 1071.4437 | L16: ='bs drivers'!L186 -> 1051.1668
B17: EBIT | C17: =C15-C16 -> 16149.24 | D17: =D15-D16 -> 17536.43 | E17: =E15-E16 -> 20180.2 | F17: =F15-F16 -> 23969.35 | G17: =G15-G16 -> 26438.38 | H17: =H15-H16 -> 31848.196 | I17: =I15-I16 -> 31380.963 | J17: =J15-J16 -> 30122.424 | ... L17: =L15-L16 -> 21268.476
B18: Finance costs | C18: ='p&l'!C20 -> 3913.44 | D18: ='p&l'!D20 -> 3125.7 | E18: ='p&l'!E20 -> 3207.16 | F18: ='p&l'!F20 -> 3545.85 | G18: ='p&l'!G20 -> 3334.37 | H18: ='bs drivers'!H225 -> 3734.2674 | I18: ='bs drivers'!I225 -> 2987.4139 | J18: ='bs drivers'!J225 -> 2240.5604 | K18: ='bs drivers'!K225 -> 1493.707 | L18: ='bs drivers'!L225 -> 746.85348
B19: Profit before tax | C19: =C17-C18 -> 12235.8 | D19: =D17-D18 -> 14410.73 | E19: =E17-E18 -> 16973.04 | F19: =F17-F18 -> 20423.5 | G19: =G17-G18 -> 23104.01 | H19: =H17-H18 -> 28113.929 | I19: =I17-I18 -> 28393.549 | J19: =J17-J18 -> 27881.864 | ... L19: =L17-L18 -> 20521.622
B20: Tax expense | C20: ='p&l'!C26 -> 4010.82 | D20: ='p&l'!D26 -> 4216.61 | E20: ='p&l'!E26 -> 4484.16 | F20: ='p&l'!F26 -> 4947.39 | G20: ='p&l'!G26 -> 5891.4 | H20: ='p&L drivers'!H24 -> 7427.506 | I20: ='p&L drivers'!I24 -> 7501.3796 | J20: ='p&L drivers'!J24 -> 7366.1959 | K20: ='p&L drivers'!K24 -> 6456.9539 | L20: ='p&L drivers'!L24 -> 5421.6709
B21: Profit after tax | C21: =C19-C20 -> 8224.98 | D21: =D19-D20 -> 10194.12 | E21: =E19-E20 -> 12488.88 | F21: =F19-F20 -> 15476.11 | G21: =G19-G20 -> 17212.61 | H21: =H19-H20 -> 20686.423 | I21: =I19-I20 -> 20892.169 | J21: =J19-J20 -> 20515.668 | ... L21: =L19-L20 -> 15099.951
B22: Share in profit/(loss) after tax of joint ventures/associates (net) | C22: ='p&l'!C28 -> 14.4 | D22: ='p&l'!D28 -> 128.19 | E22: ='p&l'!E28 -> -94.25 | F22: ='p&l'!F28 -> -22.62 | G22: ='p&l'!G28 -> -14.06 | H22: =G22 -> -14.06 | I22: =H22 -> -14.06 | J22: =I22 -> -14.06 | K22: =J22 -> -14.06 | L22: =K22 -> -14.06
B23: Profit for the period (Net Income) | C23: =C21+C22 -> 8239.38 | D23: =D21+D22 -> 10322.31 | E23: =E21+E22 -> 12394.63 | F23: =F21+F22 -> 15453.49 | G23: =G21+G22 -> 17198.55 | H23: =H21+H22 -> 20672.363 | I23: =I21+I22 -> 20878.109 | J23: =J21+J22 -> 20501.608 | ... L23: =L21+L22 -> 15085.891
B24: Dividend Paid | C24: =C21*C28 -> 3618.9912 | D24: =D21*D28 -> 3669.8832 | E24: =E21*E28 -> 3996.4416 | F24: =F21*F28 -> 5571.3996 | G24: =G21*G28 -> 5335.9091 | H24: =H21*H28 -> 7405.7395 | I24: =I21*I28 -> 7479.3966 | J24: =J21*J28 -> 7344.6091 | ... L24: =L21*L28 -> 5405.7826
B25: Transfer to Reserve | C25: =C21-C24 -> 4605.9888 | D25: =D21-D24 -> 6524.2368 | E25: =E21-E24 -> 8492.4384 | F25: =F21-F24 -> 9904.7104 | G25: =G21-G24 -> 11876.701 | H25: =H21-H24 -> 13280.684 | I25: =I21-I24 -> 13412.773 | J25: =J21-J24 -> 13171.059 | ... L25: =L21-L24 -> 9694.1687
B28: Dividend Payout % | C28: 0.44 | D28: 0.36 | E28: 0.32 | F28: 0.36 | G28: 0.31 | H28: =AVERAGE($C$28:$G$28) -> 0.358 | I28: =AVERAGE($C$28:$G$28) -> 0.358 | J28: =AVERAGE($C$28:$G$28) -> 0.358 | K28: =AVERAGE($C$28:$G$28) -> 0.358 | L28: =AVERAGE($C$28:$G$28) -> 0.358
B29: Adjustment Into R&S | D29: =D30-D25 -> 14.7932 | E29: =E30-E25 -> -1574.2384 | F29: =F30-F25 -> -12865.25 | G29: =G30-G25 -> -580.4509 | H29: =H30-H25 -> 0 | I29: =I30-I25 -> 0 | J29: =J30-J25 -> 0 | K29: =K30-K25 -> 0 | L29: =L30-L25 -> -1.4551915e-11
B30: Diff in Reserve and surplus | D30: ='balance sheet1'!D76-'balance sheet1'!C76 -> 6539.03 | E30: ='balance sheet1'!E76-'balance sheet1'!D76 -> 6918.2 | F30: ='balance sheet1'!F76-'balance sheet1'!E76 -> -2960.54 | G30: ='balance sheet1'!G76-'balance sheet1'!F76 -> 11296.25 | H30: ='balance sheet1'!H76-'balance sheet1'!G76 -> 13280.684 | I30: ='balance sheet1'!I76-'balance sheet1'!H76 -> 13412.773 | J30: ='balance sheet1'!J76-'balance sheet1'!I76 -> 13171.059 | K30: ='balance sheet1'!K76-'balance sheet1'!J76 -> 11545.297 | L30: ='balance sheet1'!L76-'balance sheet1'!K76 -> 9694.1687

Sheet cashflow1
B3: Cash Flow Statement
B4: All the Figures In Crores
B5: Financial Year | C5: 44389 | D5: =C5+365 -> 44754 | E5: =D5+365 -> 45119 | F5: =E5+365 -> 45484 | G5: =F5+365 -> 45849 | H5: =G5+365 -> 46214 | I5: =H5+365 -> 46579 | J5: =I5+365 -> 46944 | K5: =J5+365 -> 47309 | L5: =K5+365 -> 47674
B6: Cash Flow From Operating Avtivities
B7: Net Income | C7: ='income statement'!C21 -> 8224.98 | D7: ='income statement'!D21 -> 10194.12 | E7: ='income statement'!E21 -> 12488.88 | F7: ='income statement'!F21 -> 15476.11 | G7: ='income statement'!G21 -> 17212.61 | H7: ='income statement'!H21 -> 20686.423 | I7: ='income statement'!I21 -> 20892.169 | J7: ='income statement'!J21 -> 20515.668 | ... L7: ='income statement'!L21 -> 15099.951
B8: Add: Depreciation | D8: ='income statement'!D16 -> 2947.95 | E8: ='income statement'!E16 -> 3502.25 | F8: ='income statement'!F16 -> 3682.33 | G8: ='income statement'!G16 -> 4121.18 | H8: ='income statement'!H16 -> 1111.1423 | I8: ='income statement'!I16 -> 1100.9859 | J8: ='income statement'!J16 -> 1078.0277 | K8: ='income statement'!K16 -> 1071.4437 | L8: ='income statement'!L16 -> 1051.1668
B9: Add: Interest | D9: ='income statement'!D18 -> 3125.7 | E9: ='income statement'!E18 -> 3207.16 | F9: ='income statement'!F18 -> 3545.85 | G9: ='income statement'!G18 -> 3334.37 | H9: ='income statement'!H18 -> 3734.2674 | I9: ='income statement'!I18 -> 2987.4139 | J9: ='income statement'!J18 -> 2240.5604 | K9: ='income statement'!K18 -> 1493.707 | L9: ='income statement'!L18 -> 746.85348
B10: Add: Tax | D10: ='income statement'!D20 -> 4216.61 | E10: ='income statement'!E20 -> 4484.16 | F10: ='income statement'!F20 -> 4947.39 | G10: ='income statement'!G20 -> 5891.4 | H10: ='income statement'!H20 -> 7427.506 | I10: ='income statement'!I20 -> 7501.3796 | J10: ='income statement'!J20 -> 7366.1959 | K10: ='income statement'!K20 -> 6456.9539 | L10: ='income statement'!L20 -> 5421.6709
B11: Inventories | D11: ='balance sheet1'!C7-'balance sheet1'!D7 -> -122.78 | E11: ='balance sheet1'!D7-'balance sheet1'!E7 -> -885.46 | F11: ='balance sheet1'!E7-'balance sheet1'!F7 -> 208.59 | G11: ='balance sheet1'!F7-'balance sheet1'!G7 -> -1050.36 | H11: ='balance sheet1'!G7-'balance sheet1'!H7 -> -3738.0926 | I11: ='balance sheet1'!H7-'balance sheet1'!I7 -> -1509.8265 | J11: ='balance sheet1'!I7-'balance sheet1'!J7 -> -1553.5189 | K11: ='balance sheet1'!J7-'balance sheet1'!K7 -> -1509.2237 | L11: ='balance sheet1'!K7-'balance sheet1'!L7 -> -1367.2756
B12: Trade receivables | D12: ='balance sheet1'!C9-'balance sheet1'!D9 -> -3909.54 | E12: ='balance sheet1'!D9-'balance sheet1'!E9 -> 1407.79 | F12: ='balance sheet1'!E9-'balance sheet1'!F9 -> -4039.42 | G12: ='balance sheet1'!F9-'balance sheet1'!G9 -> -4942.73 | H12: ='balance sheet1'!G9-'balance sheet1'!H9 -> -19911.059 | I12: ='balance sheet1'!H9-'balance sheet1'!I9 -> -8937.9786 | J12: ='balance sheet1'!I9-'balance sheet1'!J9 -> -9376.9625 | K12: ='balance sheet1'!J9-'balance sheet1'!K9 -> -8989.2693 | L12: ='balance sheet1'!K9-'balance sheet1'!L9 -> -8908.2918
B13: Other bank balances | D13: ='balance sheet1'!C11-'balance sheet1'!D11 -> -2314.95 | E13: ='balance sheet1'!D11-'balance sheet1'!E11 -> -409.98 | F13: ='balance sheet1'!E11-'balance sheet1'!F11 -> 2193.02 | G13: ='balance sheet1'!F11-'balance sheet1'!G11 -> -7378.45 | H13: ='balance sheet1'!G11-'balance sheet1'!H11 -> 2596.7346 | I13: ='balance sheet1'!H11-'balance sheet1'!I11 -> -993.2397 | J13: ='balance sheet1'!I11-'balance sheet1'!J11 -> -1042.0221 | K13: ='balance sheet1'!J11-'balance sheet1'!K11 -> -998.93942 | L13: ='balance sheet1'!K11-'balance sheet1'!L11 -> -989.94074
B14: Other financial assets | D14: ='balance sheet1'!C14-'balance sheet1'!D14 -> -404.14 | E14: ='balance sheet1'!D14-'balance sheet1'!E14 -> -1274.28 | F14: ='balance sheet1'!E14-'balance sheet1'!F14 -> -633.82 | G14: ='balance sheet1'!F14-'balance sheet1'!G14 -> 144.03 | H14: ='balance sheet1'!G14-'balance sheet1'!H14 -> 0 | I14: ='balance sheet1'!H14-'balance sheet1'!I14 -> 0 | J14: ='balance sheet1'!I14-'balance sheet1'!J14 -> 0 | K14: ='balance sheet1'!J14-'balance sheet1'!K14 -> 0 | L14: ='balance sheet1'!K14-'balance sheet1'!L14 -> 0
B15: Provisions | D15: ='balance sheet1'!D67-'balance sheet1'!C67 -> 43.99 | E15: ='balance sheet1'!E67-'balance sheet1'!D67 -> 52.22 | F15: ='balance sheet1'!F67-'balance sheet1'!E67 -> 117.39 | G15: ='balance sheet1'!G67-'balance sheet1'!F67 -> 136.63 | H15: ='balance sheet1'!H67-'balance sheet1'!G67 -> 0 | I15: ='balance sheet1'!I67-'balance sheet1'!H67 -> 0 | J15: ='balance sheet1'!J67-'balance sheet1'!I67 -> 0 | K15: ='balance sheet1'!K67-'balance sheet1'!J67 -> 0 | L15: ='balance sheet1'!L67-'balance sheet1'!K67 -> 0
B16: Other current assets | D16: ='balance sheet1'!C15-'balance sheet1'!D15 -> -5540.07 | E16: ='balance sheet1'!D15-'balance sheet1'!E15 -> -5588.84 | F16: ='balance sheet1'!E15-'balance sheet1'!F15 -> -5470.64 | G16: ='balance sheet1'!F15-'balance sheet1'!G15 -> -4168.8 | H16: ='balance sheet1'!G15-'balance sheet1'!H15 -> 0 | I16: ='balance sheet1'!H15-'balance sheet1'!I15 -> 0 | J16: ='balance sheet1'!I15-'balance sheet1'!J15 -> 0 | K16: ='balance sheet1'!J15-'balance sheet1'!K15 -> 0 | L16: ='balance sheet1'!K15-'balance sheet1'!L15 -> 0
B17: Due to micro and small enterprises | D17: ='balance sheet1'!D51-'balance sheet1'!C51 -> 86.92 | E17: ='balance sheet1'!E51-'balance sheet1'!D51 -> 275.79 | F17: ='balance sheet1'!F51-'balance sheet1'!E51 -> 167.01 | G17: ='balance sheet1'!G51-'balance sheet1'!F51 -> 398.94 | H17: ='balance sheet1'!H51-'balance sheet1'!G51 -> -91.076945 | I17: ='balance sheet1'!I51-'balance sheet1'!H51 -> 217.02884 | J17: ='balance sheet1'!J51-'balance sheet1'!I51 -> 243.63795 | K17: ='balance sheet1'!K51-'balance sheet1'!J51 -> 182.46641 | L17: ='balance sheet1'!L51-'balance sheet1'!K51 -> 188.2111
B18: Due to others | D18: ='balance sheet1'!D52-'balance sheet1'!C52 -> 5533.47 | E18: ='balance sheet1'!E52-'balance sheet1'!D52 -> -1857.29 | F18: ='balance sheet1'!F52-'balance sheet1'!E52 -> 3341.75 | G18: ='balance sheet1'!G52-'balance sheet1'!F52 -> -1232.48 | H18: ='balance sheet1'!H52-'balance sheet1'!G52 -> 31704.804 | I18: ='balance sheet1'!I52-'balance sheet1'!H52 -> 5723.5664 | J18: ='balance sheet1'!J52-'balance sheet1'!I52 -> 5076.6002 | K18: ='balance sheet1'!K52-'balance sheet1'!J52 -> 7512.9971 | L18: ='balance sheet1'!L52-'balance sheet1'!K52 -> 9653.6385
B19: Other financial liabilities | D19: ='balance sheet1'!D66-'balance sheet1'!C66 -> -63.8 | E19: ='balance sheet1'!E66-'balance sheet1'!D66 -> 150.02 | F19: ='balance sheet1'!F66-'balance sheet1'!E66 -> -176.89 | G19: ='balance sheet1'!G66-'balance sheet1'!F66 -> 156.11 | H19: ='balance sheet1'!H66-'balance sheet1'!G66 -> 0 | I19: ='balance sheet1'!I66-'balance sheet1'!H66 -> 0 | J19: ='balance sheet1'!J66-'balance sheet1'!I66 -> 0 | K19: ='balance sheet1'!K66-'balance sheet1'!J66 -> 0 | L19: ='balance sheet1'!L66-'balance sheet1'!K66 -> 0
B20: Deferred tax liabilities (net) | D20: ='balance sheet1'!D68-'balance sheet1'!C68 -> -139.33 | E20: ='balance sheet1'!E68-'balance sheet1'!D68 -> -408.9 | F20: ='balance sheet1'!F68-'balance sheet1'!E68 -> -96.8 | G20: ='balance sheet1'!G68-'balance sheet1'!F68 -> -123.62 | H20: ='balance sheet1'!H68-'balance sheet1'!G68 -> 331.04112 | I20: ='balance sheet1'!I68-'balance sheet1'!H68 -> 598.32296 | J20: ='balance sheet1'!J68-'balance sheet1'!I68 -> 1081.4075 | K20: ='balance sheet1'!K68-'balance sheet1'!J68 -> 1954.5335 | L20: ='balance sheet1'!L68-'balance sheet1'!K68 -> 3532.6193
B21: Other non-current liabilities | D21: ='balance sheet1'!D69-'balance sheet1'!C69 -> -47.43 | E21: ='balance sheet1'!E69-'balance sheet1'!D69 -> 60.46 | F21: ='balance sheet1'!F69-'balance sheet1'!E69 -> 536.29 | G21: ='balance sheet1'!G69-'balance sheet1'!F69 -> -23.28 | H21: ='balance sheet1'!H69-'balance sheet1'!G69 -> 0 | I21: ='balance sheet1'!I69-'balance sheet1'!H69 -> 0 | J21: ='balance sheet1'!J69-'balance sheet1'!I69 -> 0 | K21: ='balance sheet1'!K69-'balance sheet1'!J69 -> 0 | L21: ='balance sheet1'!L69-'balance sheet1'!K69 -> 0
B22: Other financial liabilities | D22: ='balance sheet1'!D54-'balance sheet1'!C54 -> 1335.42 | E22: ='balance sheet1'!E54-'balance sheet1'!D54 -> 777.59 | F22: ='balance sheet1'!F54-'balance sheet1'!E54 -> 133.73 | G22: ='balance sheet1'!G54-'balance sheet1'!F54 -> -1302.3 | H22: ='balance sheet1'!H54-'balance sheet1'!G54 -> 0 | I22: ='balance sheet1'!I54-'balance sheet1'!H54 -> 0 | J22: ='balance sheet1'!J54-'balance sheet1'!I54 -> 0 | K22: ='balance sheet1'!K54-'balance sheet1'!J54 -> 0 | L22: ='balance sheet1'!L54-'balance sheet1'!K54 -> 0
B23: Other current liabilities | D23: ='balance sheet1'!D55-'balance sheet1'!C55 -> 3139.11 | E23: ='balance sheet1'!E55-'balance sheet1'!D55 -> 7757.81 | F23: ='balance sheet1'!F55-'balance sheet1'!E55 -> 10017.53 | G23: ='balance sheet1'!G55-'balance sheet1'!F55 -> 11142.89 | H23: ='balance sheet1'!H55-'balance sheet1'!G55 -> 0 | I23: ='balance sheet1'!I55-'balance sheet1'!H55 -> 0 | J23: ='balance sheet1'!J55-'balance sheet1'!I55 -> 0 | K23: ='balance sheet1'!K55-'balance sheet1'!J55 -> 0 | L23: ='balance sheet1'!L55-'balance sheet1'!K55 -> 0
B24: Provisions | D24: ='balance sheet1'!D56-'balance sheet1'!C56 -> 357.18 | E24: ='balance sheet1'!E56-'balance sheet1'!D56 -> 137.61 | F24: ='balance sheet1'!F56-'balance sheet1'!E56 -> 622.42 | G24: ='balance sheet1'!G56-'balance sheet1'!F56 -> 575.78 | H24: ='balance sheet1'!H56-'balance sheet1'!G56 -> 0 | I24: ='balance sheet1'!I56-'balance sheet1'!H56 -> 0 | J24: ='balance sheet1'!J56-'balance sheet1'!I56 -> 0 | K24: ='balance sheet1'!K56-'balance sheet1'!J56 -> 0 | L24: ='balance sheet1'!L56-'balance sheet1'!K56 -> 0
B25: Current tax liabilities (net) | D25: ='balance sheet1'!D57-'balance sheet1'!C57 -> 138.8 | E25: ='balance sheet1'!E57-'balance sheet1'!D57 -> 83.64 | F25: ='balance sheet1'!F57-'balance sheet1'!E57 -> 467.01 | G25: ='balance sheet1'!G57-'balance sheet1'!F57 -> 718.74 | H25: ='balance sheet1'!H57-'balance sheet1'!G57 -> 0 | I25: ='balance sheet1'!I57-'balance sheet1'!H57 -> 0 | J25: ='balance sheet1'!J57-'balance sheet1'!I57 -> 0 | K25: ='balance sheet1'!K57-'balance sheet1'!J57 -> 0 | L25: ='balance sheet1'!L57-'balance sheet1'!K57 -> 0
B26: Net Cash Inflow/(Outflow) from Operating Activities | D26: =SUM(D7:D25) -> 18577.23 | E26: =SUM(E7:E25) -> 23960.63 | F26: =SUM(F7:F25) -> 35038.85 | G26: =SUM(G7:G25) -> 23610.66 | H26: =SUM(H7:H25) -> 43851.69 | I26: =SUM(I7:I25) -> 27579.822 | J26: =SUM(J7:J25) -> 25629.594 | K26: =SUM(K7:K25) -> 25157.998 | L26: =SUM(L7:L25) -> 24428.603
B28: Cash Flow From Investing Activities
B29: CapEx (Tangible Assets) | D29: ='balance sheet1'!C25-'balance sheet1'!D25-'bs drivers'!D184 -> -1547.25 | E29: ='balance sheet1'!D25-'balance sheet1'!E25-'bs drivers'!E184 -> -3029.79 | F29: ='balance sheet1'!E25-'balance sheet1'!F25-'bs drivers'!F184 -> -2827.88 | G29: ='balance sheet1'!F25-'balance sheet1'!G25-'bs drivers'!G184 -> -2661.42 | H29: ='balance sheet1'!G25-'balance sheet1'!H25-'bs drivers'!H184 -> -779.89651 | I29: ='balance sheet1'!H25-'balance sheet1'!I25-'bs drivers'!I184 -> -790.66403 | J29: ='balance sheet1'!I25-'balance sheet1'!J25-'bs drivers'!J184 -> -800.7121 | K29: ='balance sheet1'!J25-'balance sheet1'!K25-'bs drivers'!K184 -> -812.26969 | L29: ='balance sheet1'!K25-'balance sheet1'!L25-'bs drivers'!L184 -> -820.35947
B30: Addition (Intangible Assets) | D30: ='balance sheet1'!C28-'balance sheet1'!D28-'bs drivers'!D185 -> -408.18 | E30: ='balance sheet1'!D28-'balance sheet1'!E28-'bs drivers'!E185 -> -54.97 | F30: ='balance sheet1'!E28-'balance sheet1'!F28-'bs drivers'!F185 -> -920.11 | G30: ='balance sheet1'!F28-'balance sheet1'!G28-'bs drivers'!G185 -> -1757.42 | H30: ='balance sheet1'!G28-'balance sheet1'!H28-'bs drivers'!H185 -> -177.59234 | I30: ='balance sheet1'!H28-'balance sheet1'!I28-'bs drivers'!I185 -> -174.91125 | J30: ='balance sheet1'!I28-'balance sheet1'!J28-'bs drivers'!J185 -> -173.11721 | K30: ='balance sheet1'!J28-'balance sheet1'!K28-'bs drivers'!K185 -> -171.05886 | L30: ='balance sheet1'!K28-'balance sheet1'!L28-'bs drivers'!L185 -> -169.30628
B31: CapEx on other Fixed Assets | D31: ='balance sheet1'!C41-'balance sheet1'!D41 -> 3450.2 | E31: ='balance sheet1'!D41-'balance sheet1'!E41 -> 3298.68 | F31: ='balance sheet1'!E41-'balance sheet1'!F41 -> -13333.72 | G31: ='balance sheet1'!F41-'balance sheet1'!G41 -> -12337.36 | H31: ='balance sheet1'!G41-'balance sheet1'!H41 -> -4705.1497 | I31: ='balance sheet1'!H41-'balance sheet1'!I41 -> -5130.8187 | J31: ='balance sheet1'!I41-'balance sheet1'!J41 -> -5615.1813 | K31: ='balance sheet1'!J41-'balance sheet1'!K41 -> -6172.0242 | L31: ='balance sheet1'!K41-'balance sheet1'!L41 -> -6816.3165
B32: Investments | D32: ='balance sheet1'!C8-'balance sheet1'!D8 -> 1211.65 | E32: ='balance sheet1'!D8-'balance sheet1'!E8 -> -5773.84 | F32: ='balance sheet1'!E8-'balance sheet1'!F8 -> 615.79 | G32: ='balance sheet1'!F8-'balance sheet1'!G8 -> -8402.99 | H32: ='balance sheet1'!G8-'balance sheet1'!H8 -> -10717.85 | I32: ='balance sheet1'!H8-'balance sheet1'!I8 -> -6565.0786 | J32: ='balance sheet1'!I8-'balance sheet1'!J8 -> -6887.5189 | K32: ='balance sheet1'!J8-'balance sheet1'!K8 -> -6602.7524 | L32: ='balance sheet1'!K8-'balance sheet1'!L8 -> -6543.2733
B33: Loans towards financing activities | D33: ='balance sheet1'!C12-'balance sheet1'!D12 -> -890.17 | E33: ='balance sheet1'!D12-'balance sheet1'!E12 -> 1808.65 | F33: ='balance sheet1'!E12-'balance sheet1'!F12 -> 5645.96 | G33: ='balance sheet1'!F12-'balance sheet1'!G12 -> -1262.92 | H33: ='balance sheet1'!G12-'balance sheet1'!H12 -> 0 | I33: ='balance sheet1'!H12-'balance sheet1'!I12 -> 0 | J33: ='balance sheet1'!I12-'balance sheet1'!J12 -> 0 | K33: ='balance sheet1'!J12-'balance sheet1'!K12 -> 0 | L33: ='balance sheet1'!K12-'balance sheet1'!L12 -> 0
B34: Other loans | D34: ='balance sheet1'!C13-'balance sheet1'!D13 -> -44.99 | E34: ='balance sheet1'!D13-'balance sheet1'!E13 -> 29.19 | F34: ='balance sheet1'!E13-'balance sheet1'!F13 -> 144.61 | G34: ='balance sheet1'!F13-'balance sheet1'!G13 -> -310.31 | H34: ='balance sheet1'!G13-'balance sheet1'!H13 -> 0 | I34: ='balance sheet1'!H13-'balance sheet1'!I13 -> 0 | J34: ='balance sheet1'!I13-'balance sheet1'!J13 -> 0 | K34: ='balance sheet1'!J13-'balance sheet1'!K13 -> 0 | L34: ='balance sheet1'!K13-'balance sheet1'!L13 -> 0
B36: Group(s) of assets classified as held for sale | D36: ='balance sheet1'!C17-'balance sheet1'!D17 -> -824.54 | E36: ='balance sheet1'!D17-'balance sheet1'!E17 -> -158.02 | F36: ='balance sheet1'!E17-'balance sheet1'!F17 -> -16.56 | G36: ='balance sheet1'!F17-'balance sheet1'!G17 -> 847.92 | H36: ='balance sheet1'!G17-'balance sheet1'!H17 -> 0 | I36: ='balance sheet1'!H17-'balance sheet1'!I17 -> 0 | J36: ='balance sheet1'!I17-'balance sheet1'!J17 -> 0 | K36: ='balance sheet1'!J17-'balance sheet1'!K17 -> 0 | L36: ='balance sheet1'!K17-'balance sheet1'!L17 -> 0
B37: Liabilities associated with group(s) of assets classified as held for sale | D37: ='balance sheet1'!D59-'balance sheet1'!C59 -> 76.53 | E37: ='balance sheet1'!E59-'balance sheet1'!D59 -> -79.73 | F37: ='balance sheet1'!F59-'balance sheet1'!E59 -> 0 | G37: ='balance sheet1'!G59-'balance sheet1'!F59 -> 0 | H37: ='balance sheet1'!H59-'balance sheet1'!G59 -> 0 | I37: ='balance sheet1'!I59-'balance sheet1'!H59 -> 0 | J37: ='balance sheet1'!J59-'balance sheet1'!I59 -> 0 | K37: ='balance sheet1'!K59-'balance sheet1'!J59 -> 0 | L37: ='balance sheet1'!L59-'balance sheet1'!K59 -> 0
B38: Net Cash Inflow/(Outflow) from Investing Activities | D38: =SUM(D29:D37) -> 1023.25 | E38: =SUM(E29:E37) -> -3959.83 | F38: =SUM(F29:F37) -> -10691.91 | G38: =SUM(G29:G37) -> -25884.5 | H38: =SUM(H29:H37) -> -16380.488 | I38: =SUM(I29:I37) -> -12661.473 | J38: =SUM(J29:J37) -> -13476.529 | K38: =SUM(K29:K37) -> -13758.105 | L38: =SUM(L29:L37) -> -14349.256
B40: Cash Flow From Financing Activities
B41: Equity share capital | D41: ='balance sheet1'!D75-'balance sheet1'!C75 -> 0.1 | E41: ='balance sheet1'!E75-'balance sheet1'!D75 -> 0.09 | F41: ='balance sheet1'!F75-'balance sheet1'!E75 -> -6.17 | G41: ='balance sheet1'!G75-'balance sheet1'!F75 -> 0.11 | H41: ='balance sheet1'!H75-'balance sheet1'!G75 -> 0 | I41: ='balance sheet1'!I75-'balance sheet1'!H75 -> 0 | J41: ='balance sheet1'!J75-'balance sheet1'!I75 -> 0 | K41: ='balance sheet1'!K75-'balance sheet1'!J75 -> 0 | L41: ='balance sheet1'!L75-'balance sheet1'!K75 -> 0
B42: Non-controlling interests | D42: ='balance sheet1'!D78-'balance sheet1'!C78 -> 914.54 | E42: ='balance sheet1'!E78-'balance sheet1'!D78 -> 1275.2 | F42: ='balance sheet1'!F78-'balance sheet1'!E78 -> 1949.15 | G42: ='balance sheet1'!G78-'balance sheet1'!F78 -> 1557.66 | H42: ='balance sheet1'!H78-'balance sheet1'!G78 -> 0 | I42: ='balance sheet1'!I78-'balance sheet1'!H78 -> 0 | J42: ='balance sheet1'!J78-'balance sheet1'!I78 -> 0 | K42: ='balance sheet1'!K78-'balance sheet1'!J78 -> 0 | L42: ='balance sheet1'!L78-'balance sheet1'!K78 -> 0
B43: Borrowings | D43: ='balance sheet1'!D64-'balance sheet1'!C64 -> -20501.73 | E43: ='balance sheet1'!E64-'balance sheet1'!D64 -> -400.63 | F43: ='balance sheet1'!F64-'balance sheet1'!E64 -> -4710.71 | G43: ='balance sheet1'!G64-'balance sheet1'!F64 -> 996.37 | H43: ='balance sheet1'!H64-'balance sheet1'!G64 -> 499.332 | I43: ='balance sheet1'!I64-'balance sheet1'!H64 -> -14500.668 | J43: ='balance sheet1'!J64-'balance sheet1'!I64 -> -14500.668 | K43: ='balance sheet1'!K64-'balance sheet1'!J64 -> -14500.668 | L43: ='balance sheet1'!L64-'balance sheet1'!K64 -> -14500.668
B44: Lease liabilities | D44: ='balance sheet1'!D65-'balance sheet1'!C65 -> 15.59 | E44: ='balance sheet1'!E65-'balance sheet1'!D65 -> 13 | F44: ='balance sheet1'!F65-'balance sheet1'!E65 -> 88.47 | G44: ='balance sheet1'!G65-'balance sheet1'!F65 -> 530.46 | H44: ='balance sheet1'!H65-'balance sheet1'!G65 -> 485.64695 | I44: ='balance sheet1'!I65-'balance sheet1'!H65 -> 187.14854 | J44: ='balance sheet1'!J65-'balance sheet1'!I65 -> 235.61695 | K44: ='balance sheet1'!K65-'balance sheet1'!J65 -> 298.62464 | L44: ='balance sheet1'!L65-'balance sheet1'!K65 -> 391.21278
B45: Borrowings | D45: ='balance sheet1'!D47-'balance sheet1'!C47 -> 2711.13 | E45: ='balance sheet1'!E47-'balance sheet1'!D47 -> 419.36 | F45: ='balance sheet1'!F47-'balance sheet1'!E47 -> -3062.05 | G45: ='balance sheet1'!G47-'balance sheet1'!F47 -> 8027.03 | H45: ='balance sheet1'!H47-'balance sheet1'!G47 -> 5211.2102 | I45: ='balance sheet1'!I47-'balance sheet1'!H47 -> 6071.7076 | J45: ='balance sheet1'!J47-'balance sheet1'!I47 -> 7076.8188 | K45: ='balance sheet1'!K47-'balance sheet1'!J47 -> 8251.1379 | L45: ='balance sheet1'!L47-'balance sheet1'!K47 -> 9623.4742
B46: Current maturities of long-term borrowings | D46: ='balance sheet1'!D48-'balance sheet1'!C48 -> 8653.57 | E46: ='balance sheet1'!E48-'balance sheet1'!D48 -> -4973.58 | F46: ='balance sheet1'!F48-'balance sheet1'!E48 -> 3299.15 | G46: ='balance sheet1'!G48-'balance sheet1'!F48 -> 6496.17 | H46: ='balance sheet1'!H48-'balance sheet1'!G48 -> -8677.5611 | I46: ='balance sheet1'!I48-'balance sheet1'!H48 -> -5158.7731 | J46: ='balance sheet1'!J48-'balance sheet1'!I48 -> -7424.879 | K46: ='balance sheet1'!K48-'balance sheet1'!J48 -> -7224.0421 | L46: ='balance sheet1'!L48-'balance sheet1'!K48 -> -7709.4448
B47: Lease liabilities | D47: ='balance sheet1'!D49-'balance sheet1'!C49 -> 0.44 | E47: ='balance sheet1'!E49-'balance sheet1'!D49 -> 84.21 | F47: ='balance sheet1'!F49-'balance sheet1'!E49 -> 56.92 | G47: ='balance sheet1'!G49-'balance sheet1'!F49 -> 36.67 | H47: ='balance sheet1'!H49-'balance sheet1'!G49 -> 111.31363 | I47: ='balance sheet1'!I49-'balance sheet1'!H49 -> 102.83777 | J47: ='balance sheet1'!J49-'balance sheet1'!I49 -> 119.86155 | K47: ='balance sheet1'!K49-'balance sheet1'!J49 -> 139.75124 | L47: ='balance sheet1'!L49-'balance sheet1'!K49 -> 162.99478
B48: Dividend Paid | D48: =-'income statement'!D24 -> -3669.8832 | E48: =-'income statement'!E24 -> -3996.4416 | F48: =-'income statement'!F24 -> -5571.3996 | G48: =-'income statement'!G24 -> -5335.9091 | H48: =-'income statement'!H24 -> -7405.7395 | I48: =-'income statement'!I24 -> -7479.3966 | J48: =-'income statement'!J24 -> -7344.6091 | K48: =-'income statement'!K24 -> -6438.0316 | L48: =-'income statement'!L24 -> -5405.7826
B49: Less: Interest Paid | D49: =-'income statement'!D18 -> -3125.7 | E49: =-'income statement'!E18 -> -3207.16 | F49: =-'income statement'!F18 -> -3545.85 | G49: =-'income statement'!G18 -> -3334.37 | H49: =-'income statement'!H18 -> -3734.2674 | I49: =-'income statement'!I18 -> -2987.4139 | J49: =-'income statement'!J18 -> -2240.5604 | K49: =-'income statement'!K18 -> -1493.707 | L49: =-'income statement'!L18 -> -746.85348
B50: Net Cash Inflow/(Outflow) from Financing Activities | D50: =SUM(D41:D49) -> -15001.943 | E50: =SUM(E41:E49) -> -10785.952 | F50: =SUM(F41:F49) -> -11502.49 | G50: =SUM(G41:G49) -> 8974.1909 | H50: =SUM(H41:H49) -> -13510.065 | I50: =SUM(I41:I49) -> -23764.558 | J50: =SUM(J41:J49) -> -24078.419 | K50: =SUM(K41:K49) -> -20966.935 | L50: =SUM(L41:L49) -> -18185.067
B52: Net Cash Flow | C52: =C26+C38+C50 -> 0 | D52: =D26+D38+D50 -> 4598.5368 | E52: =E26+E38+E50 -> 9214.8484 | F52: =F26+F38+F50 -> 12844.45 | G52: =G26+G38+G50 -> 6700.3509 | H52: =H26+H38+H50 -> 13961.137 | I52: =I26+I38+I50 -> -8846.2083 | J52: =J26+J38+J50 -> -11925.355 | ... L52: =L26+L38+L50 -> -8105.7193
B53: Opening Cash Flow | C53: 0 | D53: ='balance sheet1'!C10 -> 13373.52 | E53: ='balance sheet1'!D10 -> 13770.24 | F53: ='balance sheet1'!E10 -> 16926.69 | G53: ='balance sheet1'!F10 -> 11958.5 | H53: =G56 -> 12187 | I53: =H56 -> 18720.631 | J53: =I56 -> 2373.0428 | K53: =J56 -> -16918.508 | L53: =K56 -> -32942.504
B54: Adjustment in R&S | D54: ='income statement'!D29 -> 14.7932 | E54: ='income statement'!E29 -> -1574.2384 | F54: ='income statement'!F29 -> -12865.25 | G54: ='income statement'!G29 -> -580.4509 | H54: ='income statement'!H29 -> 0 | I54: ='income statement'!I29 -> 0 | J54: ='income statement'!J29 -> 0 | K54: ='income statement'!K29 -> 0 | L54: ='income statement'!L29 -> -1.4551915e-11
B55: Less: Tax | C55: 0 | D55: =-'income statement'!D20 -> -4216.61 | E55: =-'income statement'!E20 -> -4484.16 | F55: =-'income statement'!F20 -> -4947.39 | G55: =-'income statement'!G20 -> -5891.4 | H55: =-'income statement'!H20 -> -7427.506 | I55: =-'income statement'!I20 -> -7501.3796 | J55: =-'income statement'!J20 -> -7366.1959 | K55: =-'income statement'!K20 -> -6456.9539 | L55: =-'income statement'!L20 -> -5421.6709
B56: Net Cash Flow Closing Balance | C56: 0 | D56: =SUM(D52:D55) -> 13770.24 | E56: =SUM(E52:E55) -> 16926.69 | F56: =SUM(F52:F55) -> 11958.5 | G56: =SUM(G52:G55) -> 12187 | H56: =SUM(H52:H55) -> 18720.631 | I56: =SUM(I52:I55) -> 2373.0428 | J56: =SUM(J52:J55) -> -16918.508 | K56: =SUM(K52:K55) -> -32942.504 | L56: =SUM(L52:L55) -> -46469.894
D60: =D56-E53 -> 0

Sheet balance sheet1
L2: Index!A1
B3: Balance Sheet
B4: All the Figures In Crores
B5: Financial Year | C5: 44389 | D5: =C5+365 -> 44754 | E5: =D5+365 -> 45119 | F5: =E5+365 -> 45484 | G5: =F5+365 -> 45849 | H5: =G5+365 -> 46214 | I5: =H5+365 -> 46579 | J5: =I5+365 -> 46944 | K5: =J5+365 -> 47309 | L5: =K5+365 -> 47674
B6: Current Assets
B7: Inventories | C7: =bs!B25 -> 5820.54 | D7: =bs!C25 -> 5943.32 | E7: =bs!D25 -> 6828.78 | F7: =bs!E25 -> 6620.19 | G7: =bs!F25 -> 7670.55 | H7: ='bs drivers'!H6 -> 11408.643 | I7: ='bs drivers'!I6 -> 12918.469 | J7: ='bs drivers'!J6 -> 14471.988 | K7: ='bs drivers'!K6 -> 15981.212 | L7: ='bs drivers'!L6 -> 17348.487
B8: Investments | C8: =bs!B26 -> 31011.23 | D8: =bs!C26 -> 29799.58 | E8: =bs!D26 -> 35573.42 | F8: =bs!E26 -> 34957.63 | G8: =bs!F26 -> 43360.62 | H8: ='bs drivers'!H10 -> 54078.47 | I8: ='bs drivers'!I10 -> 60643.548 | J8: ='bs drivers'!J10 -> 67531.067 | K8: ='bs drivers'!K10 -> 74133.82 | L8: ='bs drivers'!L10 -> 80677.093
B9: Trade receivables | C9: =bs!B27 -> 42229.78 | D9: =bs!C27 -> 46139.32 | E9: =bs!D27 -> 44731.53 | F9: =bs!E27 -> 48770.95 | G9: =bs!F27 -> 53713.68 | H9: ='bs drivers'!H14 -> 73624.739 | I9: ='bs drivers'!I14 -> 82562.718 | J9: ='bs drivers'!J14 -> 91939.68 | K9: ='bs drivers'!K14 -> 100928.95 | L9: ='bs drivers'!L14 -> 109837.24
B10: Cash and cash equivalents | C10: =bs!B28 -> 13373.52 | D10: =bs!C28 -> 13770.24 | E10: =bs!D28 -> 16926.69 | F10: =bs!E28 -> 11958.5 | G10: =bs!F28 -> 12187 | H10: =cashflow1!H56 -> 18720.631 | I10: =cashflow1!I56 -> 2373.0428 | J10: =cashflow1!J56 -> -16918.508 | K10: =cashflow1!K56 -> -32942.504 | L10: =cashflow1!L56 -> -46469.894
B11: Other bank balances | C11: =bs!B29 -> 2867.98 | D11: =bs!C29 -> 5182.93 | E11: =bs!D29 -> 5592.91 | F11: =bs!E29 -> 3399.89 | G11: =bs!F29 -> 10778.34 | H11: ='bs drivers'!H18 -> 8181.6054 | I11: ='bs drivers'!I18 -> 9174.8451 | J11: ='bs drivers'!J18 -> 10216.867 | K11: ='bs drivers'!K18 -> 11215.807 | L11: ='bs drivers'!L18 -> 12205.747
B12: Loans towards financing activities | C12: =bs!B30 -> 41379.03 | D12: =bs!C30 -> 42269.2 | E12: =bs!D30 -> 40460.55 | F12: =bs!E30 -> 34814.59 | G12: =bs!F30 -> 36077.51 | H12: ='bs drivers'!H22 -> 36077.51 | I12: ='bs drivers'!I22 -> 36077.51 | J12: ='bs drivers'!J22 -> 36077.51 | K12: ='bs drivers'!K22 -> 36077.51 | L12: ='bs drivers'!L22 -> 36077.51
B13: Other loans | C13: =bs!B31 -> 235.35 | D13: =bs!C31 -> 280.34 | E13: =bs!D31 -> 251.15 | F13: =bs!E31 -> 106.54 | G13: =bs!F31 -> 416.85 | H13: ='bs drivers'!H24 -> 416.85 | I13: ='bs drivers'!I24 -> 416.85 | J13: ='bs drivers'!J24 -> 416.85 | K13: ='bs drivers'!K24 -> 416.85 | L13: ='bs drivers'!L24 -> 416.85
B14: Other financial assets | C14: =bs!B32 -> 3251.68 | D14: =bs!C32 -> 3655.82 | E14: =bs!D32 -> 4930.1 | F14: =bs!E32 -> 5563.92 | G14: =bs!F32 -> 5419.89 | H14: ='bs drivers'!H26 -> 5419.89 | I14: ='bs drivers'!I26 -> 5419.89 | J14: ='bs drivers'!J26 -> 5419.89 | K14: ='bs drivers'!K26 -> 5419.89 | L14: ='bs drivers'!L26 -> 5419.89
B15: Other current assets | C15: =bs!B33 -> 54791.48 | D15: =bs!C33 -> 60331.55 | E15: =bs!D33 -> 65920.39 | F15: =bs!E33 -> 71391.03 | G15: =bs!F33 -> 75559.83 | H15: ='bs drivers'!H28 -> 75559.83 | I15: ='bs drivers'!I28 -> 75559.83 | J15: ='bs drivers'!J28 -> 75559.83 | K15: ='bs drivers'!K28 -> 75559.83 | L15: ='bs drivers'!L28 -> 75559.83
B16: Sub-total Current Assets | C16: =SUM(C7:C15) -> 194960.59 | D16: =SUM(D7:D15) -> 207372.3 | E16: =SUM(E7:E15) -> 221215.52 | F16: =SUM(F7:F15) -> 217583.24 | G16: =SUM(G7:G15) -> 245184.27 | H16: =SUM(H7:H15) -> 283488.17 | I16: =SUM(I7:I15) -> 285146.7 | J16: =SUM(J7:J15) -> 284715.17 | ... L16: =SUM(L7:L15) -> 291072.75
B17: Group(s) of assets classified as held for sale | C17: =bs!B35 -> 6.24 | D17: =bs!C35 -> 830.78 | E17: =bs!D35 -> 988.8 | F17: =bs!E35 -> 1005.36 | G17: =bs!F35 -> 157.44 | H17: =G17 -> 157.44 | I17: =H17 -> 157.44 | J17: =I17 -> 157.44 | K17: =J17 -> 157.44 | L17: =K17 -> 157.44
B20: Total Current Assets | C20: =C16+C17 -> 194966.83 | D20: =D16+D17 -> 208203.08 | E20: =E16+E17 -> 222204.32 | F20: =F16+F17 -> 218588.6 | G20: =G16+G17 -> 245341.71 | H20: =H16+H17 -> 283645.61 | I20: =I16+I17 -> 285304.14 | J20: =J16+J17 -> 284872.61 | ... L20: =L16+L17 -> 291230.19
B22: Non-Current Assets
B23: Property, plant & equipment | C23: =bs!B7 -> 11386.29 | D23: =bs!C7 -> 10577.98 | E23: =bs!D7 -> 11336.28 | F23: =bs!E7 -> 13297.64 | G23: =bs!F7 -> 14128.56 | H23: ='bs drivers'!H58 -> 14043.766 | I23: ='bs drivers'!I58 -> 13974.033 | J23: ='bs drivers'!J58 -> 13932.585 | K23: ='bs drivers'!K58 -> 13904.398 | L23: ='bs drivers'!L58 -> 13900.171
B24: Investment property | C24: =bs!B9 -> 3646.78 | D24: =bs!C9 -> 3962.98 | E24: =bs!D9 -> 3360.22 | F24: =bs!E9 -> 1936.44 | G24: =bs!F9 -> 1157.33 | H24: ='bs drivers'!H75 -> 1099.4635 | I24: ='bs drivers'!I75 -> 1044.4903 | J24: ='bs drivers'!J75 -> 992.26581 | K24: ='bs drivers'!K75 -> 942.65252 | L24: ='bs drivers'!L75 -> 895.51989
B25: Total Tangible Assets | C25: =SUM(C23:C24) -> 15033.07 | D25: =SUM(D23:D24) -> 14540.96 | E25: =SUM(E23:E24) -> 14696.5 | F25: =SUM(F23:F24) -> 15234.08 | G25: =SUM(G23:G24) -> 15285.89 | H25: =SUM(H23:H24) -> 15143.23 | I25: =SUM(I23:I24) -> 15018.523 | J25: =SUM(J23:J24) -> 14924.851 | ... L25: =SUM(L23:L24) -> 14795.691
B26: Other intangible assets | C26: =bs!B12 -> 19197.76 | D26: =bs!C12 -> 18729.37 | E26: =bs!D12 -> 18007.98 | F26: =bs!E12 -> 17384.52 | G26: =bs!F12 -> 17050.76 | H26: ='bs drivers'!H91 -> 17050.76 | I26: ='bs drivers'!I91 -> 17050.76 | J26: ='bs drivers'!J91 -> 17050.76 | K26: ='bs drivers'!K91 -> 17050.76 | L26: ='bs drivers'!L91 -> 17050.76
B27: Right-of-use assets | C27: =bs!B14 -> 2021.53 | D27: =bs!C14 -> 1989.51 | E27: =bs!D14 -> 2137.87 | F27: =bs!E14 -> 2289.41 | G27: =bs!F14 -> 2869.02 | H27: ='bs drivers'!H99 -> 2858.027 | I27: ='bs drivers'!I99 -> 2847.3225 | J27: ='bs drivers'!J99 -> 2836.7969 | K27: ='bs drivers'!K99 -> 2826.4821 | L27: ='bs drivers'!L99 -> 2816.3406
B28: Total Intangible Assets | C28: =SUM(C26:C27) -> 21219.29 | D28: =SUM(D26:D27) -> 20718.88 | E28: =SUM(E26:E27) -> 20145.85 | F28: =SUM(F26:F27) -> 19673.93 | G28: =SUM(G26:G27) -> 19919.78 | H28: =SUM(H26:H27) -> 19908.787 | I28: =SUM(I26:I27) -> 19898.082 | J28: =SUM(J26:J27) -> 19887.557 | ... L28: =SUM(L26:L27) -> 19867.101
B29: Capital work-in-progress | C29: =bs!B8 -> 388.37 | D29: =bs!C8 -> 1170.32 | E29: =bs!D8 -> 2949.09 | F29: =bs!E8 -> 2897.04 | G29: =bs!F8 -> 2390.86 | H29: ='bs drivers'!H67 -> 2990.0095 | I29: ='bs drivers'!I67 -> 3739.6049 | J29: ='bs drivers'!J67 -> 4677.4978 | K29: ='bs drivers'!K67 -> 5851.082 | L29: ='bs drivers'!L67 -> 7320.2887
B30: Investment property under construction | C30: =bs!B10 -> 0 | D30: =bs!C10 -> 0 | E30: =bs!D10 -> 0 | F30: =bs!E10 -> 254.93 | G30: =bs!F10 -> 501.3 | H30: ='bs drivers'!H125 -> 501.3 | I30: ='bs drivers'!I125 -> 501.3 | J30: ='bs drivers'!J125 -> 501.3 | K30: ='bs drivers'!K125 -> 501.3 | L30: ='bs drivers'!L125 -> 501.3
B31: Goodwill | C31: =bs!B11 -> 8066.96 | D31: =bs!C11 -> 7685.17 | E31: =bs!D11 -> 7798.65 | F31: =bs!E11 -> 7800.88 | G31: =bs!F11 -> 8348.48 | H31: ='bs drivers'!H83 -> 8348.48 | I31: ='bs drivers'!I83 -> 8348.48 | J31: ='bs drivers'!J83 -> 8348.48 | K31: ='bs drivers'!K83 -> 8348.48 | L31: ='bs drivers'!L83 -> 8348.48
B32: Intangible assets under development | C32: =bs!B13 -> 112.02 | D32: =bs!C13 -> 79.23 | E32: =bs!D13 -> 116.48 | F32: =bs!E13 -> 147.97 | G32: =bs!F13 -> 197.82 | H32: ='bs drivers'!H139 -> 227.11714 | I32: ='bs drivers'!I139 -> 263.97825 | J32: ='bs drivers'!J139 -> 307.1123 | K32: ='bs drivers'!K139 -> 357.20232 | L32: ='bs drivers'!L139 -> 414.81905
B33: Investments in joint ventures & associates | C33: =bs!B15 -> 2670.26 | D33: =bs!C15 -> 2521.16 | E33: =bs!D15 -> 1304.86 | F33: =bs!E15 -> 1264.25 | G33: =bs!F15 -> 2318.42 | H33: ='bs drivers'!H107 -> 2318.42 | I33: ='bs drivers'!I107 -> 2318.42 | J33: ='bs drivers'!J107 -> 2318.42 | K33: ='bs drivers'!K107 -> 2318.42 | L33: ='bs drivers'!L107 -> 2318.42
B34: Other investments | C34: =bs!B16 -> 5945.14 | D34: =bs!C16 -> 7074.44 | E34: =bs!D16 -> 7920.03 | F34: =bs!E16 -> 9425.94 | G34: =bs!F16 -> 9126.23 | H34: ='bs drivers'!H115 -> 10158.407 | I34: ='bs drivers'!I115 -> 11307.322 | J34: ='bs drivers'!J115 -> 12586.181 | K34: ='bs drivers'!K115 -> 14009.678 | L34: ='bs drivers'!L115 -> 15594.172
B35: Loans towards financing activities | C35: =bs!B17 -> 52631.67 | D35: =bs!C17 -> 46736.84 | E35: =bs!D17 -> 40920.92 | F35: =bs!E17 -> 52154.76 | G35: =bs!F17 -> 62847.35 | H35: ='bs drivers'!H123 -> 65694.335 | I35: ='bs drivers'!I123 -> 68670.288 | J35: ='bs drivers'!J123 -> 71781.052 | K35: ='bs drivers'!K123 -> 75032.734 | L35: ='bs drivers'!L123 -> 78431.717
B36: Other loans | C36: =bs!B18 -> 173.24 | D36: =bs!C18 -> 284.54 | E36: =bs!D18 -> 356 | F36: =bs!E18 -> 475.46 | G36: =bs!F18 -> 348.96 | H36: ='bs drivers'!H147 -> 415.71605 | I36: ='bs drivers'!I147 -> 495.24253 | J36: ='bs drivers'!J147 -> 589.98242 | K36: ='bs drivers'!K147 -> 702.84606 | L36: ='bs drivers'!L147 -> 837.30051
B37: Other financial assets | C37: =bs!B19 -> 1420.19 | D37: =bs!C19 -> 2134.9 | E37: =bs!D19 -> 1965.78 | F37: =bs!E19 -> 1952.08 | G37: =bs!F19 -> 1863.04 | H37: ='bs drivers'!H155 -> 1993.8254 | I37: ='bs drivers'!I155 -> 2133.792 | J37: ='bs drivers'!J155 -> 2283.5841 | K37: ='bs drivers'!K155 -> 2443.8918 | L37: ='bs drivers'!L155 -> 2615.453
B38: Deferred tax assets (net) | C38: =bs!B20 -> 2697 | D38: =bs!C20 -> 2840.1 | E38: =bs!D20 -> 3984.79 | F38: =bs!E20 -> 3863.72 | G38: =bs!F20 -> 3792.88 | H38: =G38 -> 3792.88 | I38: =H38 -> 3792.88 | J38: =I38 -> 3792.88 | K38: =J38 -> 3792.88 | L38: =K38 -> 3792.88
B39: Current Tax Assets (net) | C39: =bs!B21 -> 0 | D39: =bs!C21 -> 0 | E39: =bs!D21 -> 3611.66 | F39: =bs!E21 -> 4245.78 | G39: =bs!F21 -> 4581.6 | H39: =G39 -> 4581.6 | I39: =H39 -> 4581.6 | J39: =I39 -> 4581.6 | K39: =J39 -> 4581.6 | L39: =K39 -> 4581.6
B40: Other non-current assets | C40: =bs!B22 -> 5949.67 | D40: =bs!C22 -> 6077.62 | E40: =bs!D22 -> 2377.38 | F40: =bs!E22 -> 2156.55 | G40: =bs!F22 -> 2659.78 | H40: ='bs drivers'!H176 -> 2659.78 | I40: ='bs drivers'!I176 -> 2659.78 | J40: ='bs drivers'!J176 -> 2659.78 | K40: ='bs drivers'!K176 -> 2659.78 | L40: ='bs drivers'!L176 -> 2659.78
B41: Total Other Fixed Assets: | C41: =SUM(C29:C40) -> 80054.52 | D41: =SUM(D29:D40) -> 76604.32 | E41: =SUM(E29:E40) -> 73305.64 | F41: =SUM(F29:F40) -> 86639.36 | G41: =SUM(G29:G40) -> 98976.72 | H41: =SUM(H29:H40) -> 103681.87 | I41: =SUM(I29:I40) -> 108812.69 | J41: =SUM(J29:J40) -> 114427.87 | ... L41: =SUM(L29:L40) -> 127416.21
B43: Total Non-Current Assets | C43: =C25+C28+C41 -> 116306.88 | D43: =D25+D28+D41 -> 111864.16 | E43: =E25+E28+E41 -> 108147.99 | F43: =F25+F28+F41 -> 121547.37 | G43: =G25+G28+G41 -> 134182.39 | H43: =H25+H28+H41 -> 138733.89 | I43: =I25+I28+I41 -> 143729.29 | J43: =J25+J28+J41 -> 149240.28 | ... L43: =L25+L28+L41 -> 162079
B44: Total Assets | C44: =C20+C43 -> 311273.71 | D44: =D20+D43 -> 320067.24 | E44: =E20+E43 -> 330352.31 | F44: =F20+F43 -> 340135.97 | G44: =G20+G43 -> 379524.1 | H44: =H20+H43 -> 422379.49 | I44: =I20+I43 -> 429033.44 | J44: =J20+J43 -> 434112.89 | ... L44: =L20+L43 -> 453309.2
B46: Current Liabilities
B47: Borrowings | C47: =bs!B54 -> 27765.83 | D47: =bs!C54 -> 30476.96 | E47: =bs!D54 -> 30896.32 | F47: =bs!E54 -> 27834.27 | G47: =bs!F54 -> 35861.3 | H47: ='bs drivers'!H189 -> 41072.51 | I47: ='bs drivers'!I189 -> 47144.218 | J47: ='bs drivers'!J189 -> 54221.037 | K47: ='bs drivers'!K189 -> 62472.174 | L47: ='bs drivers'!L189 -> 72095.649
B48: Current maturities of long-term borrowings | C48: =bs!B55 -> 22719.39 | D48: =bs!C55 -> 31372.96 | E48: =bs!D55 -> 26399.38 | F48: =bs!E55 -> 29698.53 | G48: =bs!F55 -> 36194.7 | H48: ='bs drivers'!H193 -> 27517.139 | I48: ='bs drivers'!I193 -> 22358.366 | J48: ='bs drivers'!J193 -> 14933.487 | K48: ='bs drivers'!K193 -> 7709.4448 | L48: ='bs drivers'!L193 -> 0
B49: Lease liabilities | C49: =bs!B56 -> 406.1 | D49: =bs!C56 -> 406.54 | E49: =bs!D56 -> 490.75 | F49: =bs!E56 -> 547.67 | G49: =bs!F56 -> 584.34 | H49: ='bs drivers'!H197 -> 695.65363 | I49: ='bs drivers'!I197 -> 798.49141 | J49: ='bs drivers'!J197 -> 918.35295 | K49: ='bs drivers'!K197 -> 1058.1042 | L49: ='bs drivers'!L197 -> 1221.099
B50: Trade payables:
B51: Due to micro and small enterprises | C51: =bs!B58 -> 488.99 | D51: =bs!C58 -> 575.91 | E51: =bs!D58 -> 851.7 | F51: =bs!E58 -> 1018.71 | G51: =bs!F58 -> 1417.65 | H51: ='bs drivers'!H201 -> 1326.5731 | I51: ='bs drivers'!I201 -> 1543.6019 | J51: ='bs drivers'!J201 -> 1787.2398 | K51: ='bs drivers'!K201 -> 1969.7063 | L51: ='bs drivers'!L201 -> 2157.9173
B52: Due to others | C52: =bs!B59 -> 45256.24 | D52: =bs!C59 -> 50789.71 | E52: =bs!D59 -> 48932.42 | F52: =bs!E59 -> 52274.17 | G52: =bs!F59 -> 51041.69 | H52: ='bs drivers'!H205 -> 82746.494 | I52: ='bs drivers'!I205 -> 88470.061 | J52: ='bs drivers'!J205 -> 93546.661 | K52: ='bs drivers'!K205 -> 101059.66 | L52: ='bs drivers'!L205 -> 110713.3
B53: Total Trade Payables | C53: =SUM(C51:C52) -> 45745.23 | D53: =SUM(D51:D52) -> 51365.62 | E53: =SUM(E51:E52) -> 49784.12 | F53: =SUM(F51:F52) -> 53292.88 | G53: =SUM(G51:G52) -> 52459.34 | H53: =SUM(H51:H52) -> 84073.067 | I53: =SUM(I51:I52) -> 90013.662 | J53: =SUM(J51:J52) -> 95333.901 | ... L53: =SUM(L51:L52) -> 112871.21
B54: Other financial liabilities | C54: =bs!B60 -> 5328.93 | D54: =bs!C60 -> 6664.35 | E54: =bs!D60 -> 7441.94 | F54: =bs!E60 -> 7575.67 | G54: =bs!F60 -> 6273.37 | H54: ='bs drivers'!H210 -> 6273.37 | I54: ='bs drivers'!I210 -> 6273.37 | J54: ='bs drivers'!J210 -> 6273.37 | K54: ='bs drivers'!K210 -> 6273.37 | L54: ='bs drivers'!L210 -> 6273.37
B55: Other current liabilities | C55: =bs!B61 -> 31269.63 | D55: =bs!C61 -> 34408.74 | E55: =bs!D61 -> 42166.55 | F55: =bs!E61 -> 52184.08 | G55: =bs!F61 -> 63326.97 | H55: ='bs drivers'!H212 -> 63326.97 | I55: ='bs drivers'!I212 -> 63326.97 | J55: ='bs drivers'!J212 -> 63326.97 | K55: ='bs drivers'!K212 -> 63326.97 | L55: ='bs drivers'!L212 -> 63326.97
B56: Provisions | C56: =bs!B62 -> 2998.68 | D56: =bs!C62 -> 3355.86 | E56: =bs!D62 -> 3493.47 | F56: =bs!E62 -> 4115.89 | G56: =bs!F62 -> 4691.67 | H56: ='bs drivers'!H214 -> 4691.67 | I56: ='bs drivers'!I214 -> 4691.67 | J56: ='bs drivers'!J214 -> 4691.67 | K56: ='bs drivers'!K214 -> 4691.67 | L56: ='bs drivers'!L214 -> 4691.67
B57: Current tax liabilities (net) | C57: =bs!B63 -> 1171.02 | D57: =bs!C63 -> 1309.82 | E57: =bs!D63 -> 1393.46 | F57: =bs!E63 -> 1860.47 | G57: =bs!F63 -> 2579.21 | H57: ='bs drivers'!H216 -> 2579.21 | I57: ='bs drivers'!I216 -> 2579.21 | J57: ='bs drivers'!J216 -> 2579.21 | K57: ='bs drivers'!K216 -> 2579.21 | L57: ='bs drivers'!L216 -> 2579.21
B58: Sub-total Current Liabilities | C58: =SUM(C47:C49)+SUM(C53:C57) -> 137404.81 | D58: =SUM(D47:D49)+SUM(D53:D57) -> 159360.85 | E58: =SUM(E47:E49)+SUM(E53:E57) -> 162065.99 | F58: =SUM(F47:F49)+SUM(F53:F57) -> 177109.46 | G58: =SUM(G47:G49)+SUM(G53:G57) -> 201970.9 | H58: =SUM(H47:H49)+SUM(H53:H57) -> 230229.59 | I58: =SUM(I47:I49)+SUM(I53:I57) -> 237185.96 | J58: =SUM(J47:J49)+SUM(J53:J57) -> 242278 | ... L58: =SUM(L47:L49)+SUM(L53:L57) -> 263059.18
B59: Liabilities associated with group(s) of assets classified as held for sale | C59: =bs!B65 -> 3.2 | D59: =bs!C65 -> 79.73 | E59: =bs!D65 -> 0 | F59: =bs!E65 -> 0 | G59: =bs!F65 -> 0 | H59: =G59 -> 0 | I59: =H59 -> 0 | J59: =I59 -> 0 | K59: =J59 -> 0 | L59: =K59 -> 0
B61: Total Current Liabilities | C61: =C58+C59 -> 137408.01 | D61: =D58+D59 -> 159440.58 | E61: =E58+E59 -> 162065.99 | F61: =F58+F59 -> 177109.46 | G61: =G58+G59 -> 201970.9 | H61: =H58+H59 -> 230229.59 | I61: =I58+I59 -> 237185.96 | J61: =J58+J59 -> 242278 | ... L61: =L58+L59 -> 263059.18
B63: Non-Current Liabilities
B64: Borrowings | C64: =bs!B46 -> 82120.04 | D64: =bs!C46 -> 61618.31 | E64: =bs!D46 -> 61217.68 | F64: =bs!E46 -> 56506.97 | G64: =bs!F46 -> 57503.34 | H64: ='bs drivers'!H224 -> 58002.672 | I64: ='bs drivers'!I224 -> 43502.004 | J64: ='bs drivers'!J224 -> 29001.336 | K64: ='bs drivers'!K224 -> 14500.668 | L64: ='bs drivers'!L224 -> 0
B65: Lease liabilities | C65: =bs!B47 -> 1617.72 | D65: =bs!C47 -> 1633.31 | E65: =bs!D47 -> 1646.31 | F65: =bs!E47 -> 1734.78 | G65: =bs!F47 -> 2265.24 | H65: ='bs drivers'!H231 -> 2750.887 | I65: ='bs drivers'!I231 -> 2938.0355 | J65: ='bs drivers'!J231 -> 3173.6524 | K65: ='bs drivers'!K231 -> 3472.2771 | L65: ='bs drivers'!L231 -> 3863.4899
B66: Other financial liabilities | C66: =bs!B48 -> 186.74 | D66: =bs!C48 -> 122.94 | E66: =bs!D48 -> 272.96 | F66: =bs!E48 -> 96.07 | G66: =bs!F48 -> 252.18 | H66: ='bs drivers'!H236 -> 252.18 | I66: ='bs drivers'!I236 -> 252.18 | J66: ='bs drivers'!J236 -> 252.18 | K66: ='bs drivers'!K236 -> 252.18 | L66: ='bs drivers'!L236 -> 252.18
B67: Provisions | C67: =bs!B49 -> 773.78 | D67: =bs!C49 -> 817.77 | E67: =bs!D49 -> 869.99 | F67: =bs!E49 -> 987.38 | G67: =bs!F49 -> 1124.01 | H67: ='bs drivers'!H238 -> 1124.01 | I67: ='bs drivers'!I238 -> 1124.01 | J67: ='bs drivers'!J238 -> 1124.01 | K67: ='bs drivers'!K238 -> 1124.01 | L67: ='bs drivers'!L238 -> 1124.01
B68: Deferred tax liabilities (net) | C68: =bs!B50 -> 1178.66 | D68: =bs!C50 -> 1039.33 | E68: =bs!D50 -> 630.43 | F68: =bs!E50 -> 533.63 | G68: =bs!F50 -> 410.01 | H68: ='bs drivers'!H240 -> 741.05112 | I68: ='bs drivers'!I240 -> 1339.3741 | J68: ='bs drivers'!J240 -> 2420.7816 | K68: ='bs drivers'!K240 -> 4375.3151 | L68: ='bs drivers'!L240 -> 7907.9344
B69: Other non-current liabilities | C69: =bs!B51 -> 68.7 | D69: =bs!C51 -> 21.27 | E69: =bs!D51 -> 81.73 | F69: =bs!E51 -> 618.02 | G69: =bs!F51 -> 594.74 | H69: ='bs drivers'!H244 -> 594.74 | I69: ='bs drivers'!I244 -> 594.74 | J69: ='bs drivers'!J244 -> 594.74 | K69: ='bs drivers'!K244 -> 594.74 | L69: ='bs drivers'!L244 -> 594.74
B71: Total Non-Current Liabilities | C71: =SUM(C64:C69) -> 85945.64 | D71: =SUM(D64:D69) -> 65252.93 | E71: =SUM(E64:E69) -> 64719.1 | F71: =SUM(F64:F69) -> 60476.85 | G71: =SUM(G64:G69) -> 62149.52 | H71: =SUM(H64:H69) -> 63465.54 | I71: =SUM(I64:I69) -> 49750.344 | J71: =SUM(J64:J69) -> 36566.7 | ... L71: =SUM(L64:L69) -> 13742.354
B72: Total Liabilities | C72: =C61+C71 -> 223353.65 | D72: =D61+D71 -> 224693.51 | E72: =E61+E71 -> 226785.09 | F72: =F61+F71 -> 237586.31 | G72: =G61+G71 -> 264120.42 | H72: =H61+H71 -> 293695.13 | I72: =I61+I71 -> 286936.3 | J72: =J61+J71 -> 278844.7 | ... L72: =L61+L71 -> 276801.54
B74: Equity
B75: Equity share capital | C75: =bs!B39 -> 280.91 | D75: =bs!C39 -> 281.01 | E75: =bs!D39 -> 281.1 | F75: =bs!E39 -> 274.93 | G75: =bs!F39 -> 275.04 | H75: ='bs drivers'!H248 -> 275.04 | I75: ='bs drivers'!I248 -> 275.04 | J75: ='bs drivers'!J248 -> 275.04 | K75: ='bs drivers'!K248 -> 275.04 | L75: ='bs drivers'!L248 -> 275.04
B76: Other equity (R&S) | C76: =bs!B40 -> 75587.62 | D76: =bs!C40 -> 82126.65 | E76: =bs!D40 -> 89044.85 | F76: =bs!E40 -> 86084.31 | G76: =bs!F40 -> 97380.56 | H76: ='bs drivers'!H249 -> 110661.24 | I76: ='bs drivers'!I249 -> 124074.02 | J76: ='bs drivers'!J249 -> 137245.07 | K76: ='bs drivers'!K249 -> 148790.37 | L76: ='bs drivers'!L249 -> 158484.54
B77: Equity attributable to owners of the Company | C77: =C76+C75 -> 75868.53 | D77: =D76+D75 -> 82407.66 | E77: =E76+E75 -> 89325.95 | F77: =F76+F75 -> 86359.24 | G77: =G76+G75 -> 97655.6 | H77: =H76+H75 -> 110936.28 | I77: =I76+I75 -> 124349.06 | J77: =J76+J75 -> 137520.11 | ... L77: =L76+L75 -> 158759.58
B78: Non-controlling interests | C78: =bs!B42 -> 12051.53 | D78: =bs!C42 -> 12966.07 | E78: =bs!D42 -> 14241.27 | F78: =bs!E42 -> 16190.42 | G78: =bs!F42 -> 17748.08 | H78: ='bs drivers'!H251 -> 17748.08 | I78: ='bs drivers'!I251 -> 17748.08 | J78: ='bs drivers'!J251 -> 17748.08 | K78: ='bs drivers'!K251 -> 17748.08 | L78: ='bs drivers'!L251 -> 17748.08
B79: Total Equity | C79: =SUM(C77:C78) -> 87920.06 | D79: =SUM(D77:D78) -> 95373.73 | E79: =SUM(E77:E78) -> 103567.22 | F79: =SUM(F77:F78) -> 102549.66 | G79: =SUM(G77:G78) -> 115403.68 | H79: =SUM(H77:H78) -> 128684.36 | I79: =SUM(I77:I78) -> 142097.14 | J79: =SUM(J77:J78) -> 155268.19 | ... L79: =SUM(L77:L78) -> 176507.66
B80: Total Liabilities & Equity | C80: =C72+C79 -> 311273.71 | D80: =D72+D79 -> 320067.24 | E80: =E72+E79 -> 330352.31 | F80: =F72+F79 -> 340135.97 | G80: =G72+G79 -> 379524.1 | H80: =H72+H79 -> 422379.49 | I80: =I72+I79 -> 429033.44 | J80: =J72+J79 -> 434112.89 | ... L80: =L72+L79 -> 453309.2
B82: Balance Check | C82: =C44-C80 -> 0 | D82: =D44-D80 -> 0 | E82: =E44-E80 -> 0 | F82: =F44-F80 -> 0 | G82: =G44-G80 -> 0 | H82: =H44-H80 -> 0 | I82: =I44-I80 -> 0 | J82: =J44-J80 -> 0 | ... L82: =L44-L80 -> 0

Sheet valuation->

Sheet wacc
B2: Weigheted Average Cost Of Capital
B3: All the figures in Rs Crores
B4: Weigheted Average Cost of Capital
B6: Equity (Cr) | D6: ='balance sheet1'!G79 -> 115403.68
B7: Debt (cr) | D7: ='balance sheet1'!G64+'balance sheet1'!G47 -> 93364.64
B9: Cost of Debt | D9: ='income statement'!C18/wacc!D7 -> 0.041915655
B10: Tax Rate | D10: ='p&L drivers'!G26 -> 0.2549947
B11: D/(D+E) | D11: =D7/(D6+D7) -> 0.44721651
B12: After Tax Cost of Debt | D12: =D9*(1-D10) -> 0.031227385
B14: Risk Free Rate (10 yr Treasury Yield) | D14: 0.065
B15: Expected Market Return | D15: 0.1259
B16: Market Risk Premium | D16: =D15-D14 -> 0.0609
B17: Beta | D17: 1
B18: E/(D+E) | D18: =1-D11 -> 0.55278349
B19: Cost of Equity | D19: =D14+(D17*D16) -> 0.1259
B21: WACC | D21: 0.081574162

Sheet dcf
L1: Index!A1
B2: Discounted Cash Flow Model
B3: All the Figures In Crores
B4: Financial Year | C4: 44389 | D4: 44754 | E4: 45119 | F4: 45484 | G4: 45849 | H4: 46214 | I4: 46579 | J4: 46944 | K4: 47309 | L4: 47674
B5: Unlevered Free Cash Flow | D5: =cashflow1!D26-cashflow1!D29-cashflow1!D30 -> 20532.66 | E5: =cashflow1!E26-cashflow1!E29-cashflow1!E30 -> 27045.39 | F5: =cashflow1!F26-cashflow1!F29-cashflow1!F30 -> 38786.84 | G5: =cashflow1!G26-cashflow1!G29-cashflow1!G30 -> 28029.5 | H5: =cashflow1!H26-cashflow1!H29-cashflow1!H30 -> 44809.179 | I5: =cashflow1!I26-cashflow1!I29-cashflow1!I30 -> 28545.397 | J5: =cashflow1!J26-cashflow1!J29-cashflow1!J30 -> 26603.423 | K5: =cashflow1!K26-cashflow1!K29-cashflow1!K30 -> 26141.326 | L5: =cashflow1!L26-cashflow1!L29-cashflow1!L30 -> 25418.269
K6: TV | L6: =L5*(1+C14)/(C15-C14) -> 845285.53
B8: Projection Year | G8: 0 | H8: 1 | I8: 2 | J8: 3 | K8: 4 | L8: 5
B9: Present Value of the Free Cash Flow | H9: =PV($C$15,H8,,-H5,) -> 41429.594 | I9: =PV($C$15,I8,,-I5,) -> 24401.891 | J9: =PV($C$15,J8,,-J5,) -> 21026.579 | K9: =PV($C$15,K8,,-K5,) -> 19103.036 | L9: =PV($C$15,L8,,-L5,) -> 17173.723
K10: pv year tv | L10: =PV(C15,L8,,-L6) -> 571112.83
B12: Implied Share Price Calculation
B13: Sum of PV of FCF | C13: =SUM(H9:L9) -> 123134.82 | F13: Sensitivity Table
B14: Growth Rate | C14: 0.05
B15: WACC | C15: =wacc!D21 -> 0.081574162 | H15: Growth
B16: Terminal Value | C16: =L6 -> 845285.53 | G16: =C24 -> 4328.051 | H16: 0.04 | I16: 0.045 | J16: 0.05 | K16: 0.055 | L16: 0.06
B17: PV of Terminal Value | C17: =L10 -> 571112.83 | F17: WACC | G17: 0.071574162 | H17: 4505.6634 | I17: 5340.8357 | J17: 6563.125 | K17: 8522.881 | L17: 12175.853
B18: Enterprice Value | C18: =C17+C13 -> 694247.65 | G18: 0.076574162 | H18: 3820.2216 | I18: 4415.8486 | J18: 5235.6134 | K18: 6435.3534 | L18: 8358.955
B19: (+) Cash | C19: ='balance sheet1'!G10 -> 12187 | G19: 0.081574162 | H19: 3299.3104 | I19: 3743.3619 | J19: 4328.051 | K19: 5132.7618 | L19: 6310.4701
B20: (-) Debt | C20: =wacc!D7 -> 93364.64 | G20: 0.086574162 | H20: 2889.946 | I20: 3232.2803 | J20: 3668.2147 | K20: 4242.2158 | L20: 5032.2166
B21: (-) Minority Interest | C21: ='balance sheet1'!G78 -> 17748.08 | G21: 0.091574162 | H21: 2559.6912 | I21: 2830.6269 | J21: 3166.7319 | K21: 3594.7337 | L21: 4158.2899
B22: Equity Value | C22: =C18+C19-C20-C21 -> 595321.93
B23: Diluted Shares Outstanding (cr.) | C23: =cca!E7 -> 137.54966
B24: Implied Share Price | C24: =C22/C23 -> 4328.051

Sheet cca
Q1: Index!A1
B2: Comperable Companies analysis
B3: All the figures in Rs Crores
C4: Market Data | K4: Financials | O4: Valuation
B5: Company | C5: Share Price (Rs./Share) | D5: Equity Value (Market Cap) | E5: No of Shares Outstanding | F5: Debt | G5: Cash Equal | H5: Net Debt | I5: Enterprice Value | K5: Revenue | L5: EBITDA | M5: Net Icome | O5: EV/Reveneu | P5: EV/EBITDA | Q5: P/E
B7: Larsen & Toubro | C7: 4068 | D7: 559552 | E7: =D7/C7 -> 137.54966 | F7: 134001.13 | G7: 22965.34 | H7: =F7-G7 -> 111035.79 | I7: =D7+H7 -> 670587.79 | K7: 255734.45 | L7: 37922.33 | M7: 17673.33 | O7: =I7/K7 -> 2.6222036 | P7: =I7/L7 -> 17.683191 | Q7: =D7/M7 -> 31.660813
B8: Hind.Aeronautics | C8: 4862.6 | D8: 325198.57 | E8: =D8/C8 -> 66.877508 | F8: 51.44 | G8: 38182.25 | H8: =F8-G8 -> -38130.81 | I8: =D8+H8 -> 287067.76 | K8: 30980.95 | L8: 12221.48 | M8: 8364.05 | O8: =I8/K8 -> 9.2659444 | P8: =I8/L8 -> 23.488789 | Q8: =D8/M8 -> 38.880515
B9: Bharat Electron | C9: 427.3 | D9: 312459.28 | E9: =D9/C9 -> 731.241 | F9: 58.89 | G9: 9545.1 | H9: =F9-G9 -> -9486.21 | I9: =D9+H9 -> 302973.07 | K9: 23768.75 | L9: 7555.83 | M9: 5322.68 | O9: =I9/K9 -> 12.746698 | P9: =I9/L9 -> 40.09792 | Q9: =D9/M9 -> 58.703375
B10: Cummins India | C10: 4414.2 | D10: 122395.39 | E10: =D10/C10 -> 27.727649 | F10: 24.35 | G10: 2510.29 | H10: =F10-G10 -> -2485.94 | I10: =D10+H10 -> 119909.45 | K10: 10390.69 | L10: 2787.52 | M10: 1999.94 | O10: =I10/K10 -> 11.540085 | P10: =I10/L10 -> 43.016534 | Q10: =D10/M10 -> 61.199531
B11: Siemens Ener.Ind | C11: 3248.2 | D11: 115675.05 | E11: =D11/C11 -> 35.612047 | F11: 133.4 | G11: 0 | H11: =F11-G11 -> 133.4 | I11: =D11+H11 -> 115808.45 | K11: 2653.4 | L11: 591.9 | M11: 408.8 | O11: =I11/K11 -> 43.645304 | P11: =I11/L11 -> 195.65543 | Q11: =D11/M11 -> 282.96245
B12: CG Power & Ind | C12: 732.95 | D12: 115454.11 | E12: =D12/C12 -> 157.51976 | F12: 116.82 | G12: 1259.12 | H12: =F12-G12 -> -1142.3 | I12: =D12+H12 -> 114311.81 | K12: 9908.66 | L12: 1445.29 | M12: 972.98 | O12: =I12/K12 -> 11.536556 | P12: =I12/L12 -> 79.092646 | Q12: =D12/M12 -> 118.66031
B13: Polycab India | C13: 7659.5 | D13: 115304.63 | E13: =D13/C13 -> 15.053806 | F13: 202.43 | G13: 770.64 | H13: =F13-G13 -> -568.21 | I13: =D13+H13 -> 114736.42 | K13: 22408.31 | L13: 3048.96 | M13: 2045.54 | O13: =I13/K13 -> 5.1202621 | P13: =I13/L13 -> 37.63133 | Q13: =D13/M13 -> 56.368797
B14: Mazagon Dock | C14: 2752.5 | D14: 111030.37 | E14: =D14/C14 -> 40.338009 | F14: 1.84 | G14: 16149.61 | H14: =F14-G14 -> -16147.77 | I14: =D14+H14 -> 94882.6 | K14: 11431.88 | L14: 3186.36 | M14: 2413.51 | O14: =I14/K14 -> 8.2998247 | P14: =I14/L14 -> 29.77774 | Q14: =D14/M14 -> 46.003692
B15: Siemens | C15: 3022 | D15: 107619.67 | E15: =D15/C15 -> 35.612068 | F15: 135 | G15: 9567.9 | H15: =F15-G15 -> -9432.9 | I15: =D15+H15 -> 98186.77 | K15: 22239.7 | L15: 3742.9 | M15: 2718.1 | O15: =I15/K15 -> 4.4149323 | P15: =I15/L15 -> 26.232806 | Q15: =D15/M15 -> 39.593713
B16: A B B | C16: 4978.5 | D16: 105474.29 | E16: =D16/C16 -> 21.185958 | F16: 73.22 | G16: 5507.82 | H16: =F16-G16 -> -5434.6 | I16: =D16+H16 -> 100039.69 | K16: 12188.31 | L16: 2664.68 | M16: 1871.64 | O16: =I16/K16 -> 8.2078393 | P16: =I16/L16 -> 37.542853 | Q16: =D16/M16 -> 56.353941
B17: High | C17: =MAX(C7:C16) -> 7659.5 | D17: =MAX(D7:D16) -> 559552 | E17: =MAX(E7:E16) -> 731.241 | F17: =MAX(F7:F16) -> 134001.13 | G17: =MAX(G7:G16) -> 38182.25 | H17: =MAX(H7:H16) -> 111035.79 | I17: =MAX(I7:I16) -> 670587.79 | K17: =MAX(K7:K16) -> 255734.45 | L17: =MAX(L7:L16) -> 37922.33 | M17: =MAX(M7:M16) -> 17673.33 | O17: =MAX(O7:O16) -> 43.645304 | P17: =MAX(P7:P16) -> 195.65543 | Q17: =MAX(Q7:Q16) -> 282.96245
B18: 75th Percentile | C18: =QUARTILE(C7:C16,3) -> 4750.5 | D18: =QUARTILE(D7:D16,3) -> 264943.31 | E18: =QUARTILE(E7:E16,3) -> 119.88162 | F18: =QUARTILE(F7:F16,3) -> 134.6 | G18: =QUARTILE(G7:G16,3) -> 14504.183 | H18: =QUARTILE(H7:H16,3) -> -711.7325 | I18: =QUARTILE(I7:I16,3) -> 245278.18 | K18: =QUARTILE(K7:K16,3) -> 23428.64 | L18: =QUARTILE(L7:L16,3) -> 6602.5975 | M18: =QUARTILE(M7:M16,3) -> 4671.535 | O18: =_xlfn.QUARTILE.EXC(O7:O16,3) -> 11.841738 | P18: =_xlfn.QUARTILE.INC(P7:P16,) -> 17.683191 | Q18: =_xlfn.QUARTILE.INC(Q7:Q16,) -> 31.660813
B19: Average | C19: =AVERAGE(C7:C16) -> 3616.575 | D19: =AVERAGE(D7:D16) -> 199016.34 | E19: =AVERAGE(E7:E16) -> 126.87175 | F19: =AVERAGE(F7:F16) -> 13479.852 | G19: =AVERAGE(G7:G16) -> 10645.807 | H19: =AVERAGE(H7:H16) -> 2834.045 | I19: =AVERAGE(I7:I16) -> 201850.38 | K19: =AVERAGE(K7:K16) -> 40170.51 | L19: =AVERAGE(L7:L16) -> 7516.725 | M19: =AVERAGE(M7:M16) -> 4379.057 | O19: =AVERAGE(O7:O16) -> 11.739965 | P19: =AVERAGE(P7:P16) -> 53.021924 | Q19: =AVERAGE(Q7:Q16) -> 79.038714
B20: Median | C20: =MEDIAN(C7:C16) -> 3658.1 | D20: =MEDIAN(D7:D16) -> 115564.58 | E20: =MEDIAN(E7:E16) -> 37.975039 | F20: =MEDIAN(F7:F16) -> 95.02 | G20: =MEDIAN(G7:G16) -> 7526.46 | H20: =MEDIAN(H7:H16) -> -3960.27 | I20: =MEDIAN(I7:I16) -> 115272.43 | K20: =MEDIAN(K7:K16) -> 17214.005 | L20: =MEDIAN(L7:L16) -> 3117.66 | M20: =MEDIAN(M7:M16) -> 2229.525 | O20: =MEDIAN(O7:O16) -> 8.7828845 | P20: =MEDIAN(P7:P16) -> 37.587092 | Q20: =MEDIAN(Q7:Q16) -> 56.361369
B21: 25 Percentile | C21: =QUARTILE(C10:C19,1) -> 3078.55 | D21: =QUARTILE(D10:D19,1) -> 112098.93 | E21: =QUARTILE(E10:E19,1) -> 29.698749 | F21: =QUARTILE(F10:F19,1) -> 84.12 | G21: =QUARTILE(G10:G19,1) -> 1571.9125 | H21: =QUARTILE(H10:H19,1) -> -4697.435 | I21: =QUARTILE(I10:I19,1) -> 103607.72 | K21: =QUARTILE(K10:K19,1) -> 10650.987 | L21: =QUARTILE(L10:L19,1) -> 2695.39 | M21: =QUARTILE(M10:M19,1) -> 1903.715 | O21: =QUARTILE(O7:O16,1) -> 5.8921564 | P21: =_xlfn.QUARTILE.INC(P7:P16,) -> 17.683191 | Q21: =_xlfn.QUARTILE.INC(Q7:Q16,) -> 31.660813
B22: Low | C22: =MIN(C7:C16) -> 427.3 | D22: =MIN(D7:D16) -> 105474.29 | E22: =MIN(E7:E16) -> 15.053806 | F22: =MIN(F7:F16) -> 1.84 | G22: =MIN(G7:G16) -> 0 | H22: =MIN(H7:H16) -> -38130.81 | I22: =MIN(I7:I16) -> 94882.6 | K22: =MIN(K7:K16) -> 2653.4 | L22: =MIN(L7:L16) -> 591.9 | M22: =MIN(M7:M16) -> 408.8 | O22: =MIN(O7:O16) -> 2.6222036 | P22: =MIN(P7:P16) -> 17.683191 | Q22: =MIN(Q7:Q16) -> 31.660813
B24: 1 | C24: 2 | D24: 3 | E24: 4 | F24: 5 | G24: 6 | H24: 7 | I24: 8 | J24: 9 | K24: 10 | L24: 11 | M24: 12 | N24: 13 | O24: 14 | P24: 15 | Q24: 16
B25: Average | C25: =VLOOKUP($B$25,$B$17:$Q$22,C24,) -> 3616.575 | D25: =VLOOKUP($B$25,$B$17:$Q$22,D24,) -> 199016.34 | E25: =VLOOKUP($B$25,$B$17:$Q$22,E24,) -> 126.87175 | F25: =VLOOKUP($B$25,$B$17:$Q$22,F24,) -> 13479.852 | G25: =VLOOKUP($B$25,$B$17:$Q$22,G24,) -> 10645.807 | H25: =VLOOKUP($B$25,$B$17:$Q$22,H24,) -> 2834.045 | I25: =VLOOKUP($B$25,$B$17:$Q$22,I24,) -> 201850.38 | J25: =VLOOKUP($B$25,$B$17:$Q$22,J24,) -> 0 | ... Q25: =VLOOKUP($B$25,$B$17:$Q$22,Q24,) -> 79.038714
B29: Enjoy Lemon Valuation | O29: EV/Revenue | P29: EV/EBITDA | Q29: P/E
B30: Implied Enterprise Value | O30: =K7*O25 -> 3002313.5 | P30: =L7*P25 -> 2010714.9 | Q30: =Q25*(M7) -> 1396877.3
B31: Net Debt | O31: =H7 -> 111035.79 | P31: =O31 -> 111035.79 | Q31: =P31 -> 111035.79
B32: Implied Market Value | O32: =O30-O31 -> 2891277.7 | P32: =P30-P31 -> 1899679.1 | Q32: =Q19*M7 -> 1396877.3
B33: Shares Outstanding | O33: =E7 -> 137.54966 | P33: =O33 -> 137.54966 | Q33: =P33 -> 137.54966
B34: Implied Value Per Share | O34: =O32/O33 -> 21019.883 | P34: =P32/P33 -> 13810.861 | Q34: =Q32/Q33 -> 10155.44

Sheet raw data ->

Sheet p&l
B3: PROFIT & LOSS
B4: Particulars | C4: 2020-21 | D4: 2021-22 | E4: 2022-23 | F4: 2023-24 | G4: 2024-25
B5: Revenue from operations (₹ crore) | C5: 135979.03 | D5: 156521.23 | E5: 183340.7 | F5: 221112.91 | G5: 255734.45
B6: Other income net (₹ crore) | C6: 3429.35 | D6: 2267.08 | E6: 2929.17 | F6: 4158.03 | G6: 4124.82
B7: Total Income (₹ crore) | C7: 139408.38 | D7: 158788.31 | E7: 186269.87 | F7: 225270.94 | G7: 259859.27
B8: Manufacturing, construction and operating expenses:
B9: - Cost of raw materials and components consumed | C9: 15562.05 | D9: 17100.84 | E9: 18995.11 | F9: 19442.25 | G9: 27655.02
B10: - Construction materials consumed | C10: 24558.23 | D10: 33506.21 | E10: 43237.35 | F10: 54813.97 | G10: 63526.44
B11: - Purchase of stock-in-trade | C11: 1213.58 | D11: 1069.5 | E11: 1052.86 | F11: 1063.77 | G11: 1402.14
B12: - Stores, spares and tools consumed | C12: 2032.89 | D12: 3091.07 | E12: 4814.89 | F12: 4432.02 | G12: 4393.39
B13: - Sub-contracting charges | C13: 22316.18 | D13: 24772.33 | E13: 25624.45 | F13: 35054.35 | G13: 40570.92
B14: - Changes in inventories (finished goods, WIP, stock-in-trade, property development) | C14: 343.37 | D14: -2076.6 | E14: -3156.64 | F14: 1021.07 | G14: -410.79
B15: - Other manufacturing, construction and operating expenses | C15: 12983.56 | D15: 16322.62 | E15: 20020.81 | F15: 24486.49 | G15: 27533.55
B16: - Finance cost of financial services business and finance lease activity | C16: 7691.04 | D16: 5952.54 | E16: 6026.44 | F16: 5714.9 | G16: 6302.23
B17: Total manufacturing, construction and operating expenses | C17: 86700.9 | D17: 99738.51 | E17: 116615.27 | F17: 146028.82 | G17: 170972.9
B18: Employee benefits expense | C18: 24750.54 | D18: 29733.53 | E18: 37214.11 | F18: 41171.02 | G18: 46768.68
B19: Sales, administration and other expenses | C19: 8903.49 | D19: 8831.89 | E19: 8758.04 | F19: 10419.42 | G19: 11558.13
B20: Finance costs | C20: 3913.44 | D20: 3125.7 | E20: 3207.16 | F20: 3545.85 | G20: 3334.37
... B30: Dividend Amount | C30: 2528 | D30: 3091.11 | E30: 3373.2 | F30: 4217 | G30: 3850

Sheet bs
A2: Balance Sheet
A4: Particulars | B4: As at 31-3-2021 (₹ crore) | C4: 2021-22 | D4: 2022-23 | E4: 2023-24 | F4: 2024-25
A5: ASSETS
A6: Non-current Assets:
A7: Property, plant & equipment | B7: 11386.29 | C7: 10577.98 | D7: 11336.28 | E7: 13297.64 | F7: 14128.56
A8: Capital work-in-progress | B8: 388.37 | C8: 1170.32 | D8: 2949.09 | E8: 2897.04 | F8: 2390.86
A9: Investment property | B9: 3646.78 | C9: 3962.98 | D9: 3360.22 | E9: 1936.44 | F9: 1157.33
A10: Investment property under construction | B10: 0 | C10: 0 | D10: 0 | E10: 254.93 | F10: 501.3
A11: Goodwill | B11: 8066.96 | C11: 7685.17 | D11: 7798.65 | E11: 7800.88 | F11: 8348.48
A12: Other intangible assets | B12: 19197.76 | C12: 18729.37 | D12: 18007.98 | E12: 17384.52 | F12: 17050.76
A13: Intangible assets under development | B13: 112.02 | C13: 79.23 | D13: 116.48 | E13: 147.97 | F13: 197.82
A14: Right-of-use assets | B14: 2021.53 | C14: 1989.51 | D14: 2137.87 | E14: 2289.41 | F14: 2869.02
A15: Investments in joint ventures & associates | B15: 2670.26 | C15: 2521.16 | D15: 1304.86 | E15: 1264.25 | F15: 2318.42
A16: Other investments | B16: 5945.14 | C16: 7074.44 | D16: 7920.03 | E16: 9425.94 | F16: 9126.23
A17: Loans towards financing activities | B17: 52631.67 | C17: 46736.84 | D17: 40920.92 | E17: 52154.76 | F17: 62847.35
A18: Other loans | B18: 173.24 | C18: 284.54 | D18: 356 | E18: 475.46 | F18: 348.96
... A23: Sub-total Non-current Assets | B23: 116306.88 | C23: 111867.75 | D23: 108147.99 | E23: 121547.37 | F23: 134182.39
A24: Current Assets:
A25: Inventories | B25: 5820.54 | C25: 5943.32 | D25: 6828.78 | E25: 6620.19 | F25: 7670.55
A26: Investments | B26: 31011.23 | C26: 29799.58 | D26: 35573.42 | E26: 34957.63 | F26: 43360.62
A27: Trade receivables | B27: 42229.78 | C27: 46139.32 | D27: 44731.53 | E27: 48770.95 | F27: 53713.68
A28: Cash and cash equivalents | B28: 13373.52 | C28: 13770.24 | D28: 16926.69 | E28: 11958.5 | F28: 12187
A29: Other bank balances | B29: 2867.98 | C29: 5182.93 | D29: 5592.91 | E29: 3399.89 | F29: 10778.34
A30: Loans towards financing activities | B30: 41379.03 | C30: 42269.2 | D30: 40460.55 | E30: 34814.59 | F30: 36077.51
A31: Other loans | B31: 235.35 | C31: 280.34 | D31: 251.15 | E31: 106.54 | F31: 416.85
A32: Other financial assets | B32: 3251.68 | C32: 3655.82 | D32: 4930.1 | E32: 5563.92 | F32: 5419.89
A33: Other current assets | B33: 54791.48 | C33: 60331.55 | D33: 65920.39 | E33: 71391.03 | F33: 75559.83
A34: Sub-total Current Assets | B34: 194960.59 | C34: 207372.3 | D34: 148466.35 | E34: 217583.24 | F34: 245184.27
A35: Group(s) of assets classified as held for sale | B35: 6.24 | C35: 830.78 | D35: 988.8 | E35: 1005.36 | F35: 157.44
A36: TOTAL ASSETS | B36: 311273.71 | C36: 320067.2 | D36: 330352.31 | E36: 339627.24 | F36: 379524.1
A37: EQUITY & LIABILITIES
A38: Equity:
A39: Equity share capital | B39: 280.91 | C39: 281.01 | D39: 281.1 | E39: 274.93 | F39: 275.04
A40: Other equity | B40: 75587.62 | C40: 82126.65 | D40: 89044.85 | E40: 86084.31 | F40: 97380.56
A41: Equity attributable to owners of the Company | B41: 75868.53 | C41: 82407.66 | D41: 89325.95 | E41: 86359.24 | F41: 97655.6
A42: Non-controlling interests | B42: 12051.53 | C42: 12966.07 | D42: 14241.27 | E42: 16190.42 | F42: 17748.08
A43: TOTAL EQUITY | B43: 87920.06 | C43: 95373.73 | D43: 103567.22 | E43: 102549.66 | F43: 115403.68
A44: Liabilities:
A45: Non-current liabilities:
A46: Borrowings | B46: 82120.04 | C46: 61618.31 | D46: 61217.68 | E46: 56506.97 | F46: 57503.34
A47: Lease liabilities | B47: 1617.72 | C47: 1633.31 | D47: 1646.31 | E47: 1734.78 | F47: 2265.24
A48: Other financial liabilities | B48: 186.74 | C48: 122.94 | D48: 272.96 | E48: 96.07 | F48: 252.18
A49: Provisions | B49: 773.78 | C49: 817.77 | D49: 869.99 | E49: 987.38 | F49: 1124.01
A50: Deferred tax liabilities (net) | B50: 1178.66 | C50: 1039.33 | D50: 630.43 | E50: 533.63 | F50: 410.01
A51: Other non-current liabilities | B51: 68.7 | C51: 21.27 | D51: 81.73 | E51: 618.02 | F51: 594.74
A52: Sub-total Non-current Liabilities | B52: 85945.64 | C52: 65363.29 | D52: 64719.1 | E52: 60476.85 | F52: 62149.52
A53: Current liabilities:
A54: Borrowings | B54: 27765.83 | C54: 30476.96 | D54: 30896.32 | E54: 27834.27 | F54: 35861.3
A55: Current maturities of long-term borrowings | B55: 22719.39 | C55: 31372.96 | D55: 26399.38 | E55: 29698.53 | F55: 36194.7
A56: Lease liabilities | B56: 406.1 | C56: 406.54 | D56: 490.75 | E56: 547.67 | F56: 584.34
A57: Trade payables:
A58: Due to micro and small enterprises | B58: 488.99 | C58: 575.91 | D58: 851.7 | E58: 1018.71 | F58: 1417.65
A59: Due to others | B59: 45256.24 | C59: 50789.71 | D59: 48932.42 | E59: 52274.17 | F59: 51041.69
A60: Other financial liabilities | B60: 5328.93 | C60: 6664.35 | D60: 7441.94 | E60: 7575.67 | F60: 6273.37
A61: Other current liabilities | B61: 31269.63 | C61: 34408.74 | D61: 42166.55 | E61: 52184.08 | F61: 63326.97
A62: Provisions | B62: 2998.68 | C62: 3355.86 | D62: 3493.47 | E62: 4115.89 | F62: 4691.67
A63: Current tax liabilities (net) | B63: 1171.02 | C63: 1309.82 | D63: 1393.46 | E63: 1860.47 | F63: 2579.21
A64: Sub-total Current Liabilities | B64: 137404.81 | C64: 159353.8 | D64: 162065.99 | E64: 177109.46 | F64: 201970.9
A65: Liabilities associated with group(s) of assets classified as held for sale | B65: 3.2 | C65: 79.73
A66: TOTAL LIABILITIES | B66: 223353.65 | C66: 224675.19 | D66: 226785.09 | E66: 237586.31 | F66: 264120.42
A67: TOTAL EQUITY & LIABILITIES | B67: 311273.71 | C67: 320048.92 | D67: 330352.31 | E67: 339627.24 | F67: 379524.1

Sheet cf
A3: Cash Flows
A5: Particulars | B5: 41699 | C5: 42064 | D5: 42430 | E5: 42795 | F5: 43160 | G5: 43525 | H5: 43891 | I5: 44256 | J5: 44621 | K5: 44986 | L5: 45352 | M5: 45717
A6: Cash from Operating Activity - | B6: -7143 | C6: -1365 | D6: -3240 | E6: 6655 | F6: -10031 | G6: -4756 | H6: 6694 | I6: 23074 | J6: 19164 | K6: 22777 | L6: 18266 | M6: 9161
A7: Profit from operations | B7: 11184 | C7: 10198 | D7: 10485 | E7: 11255 | F7: 13248 | G7: 16073 | H7: 18524 | I7: 16347 | J7: 18946 | K7: 22525 | L7: 24931 | M7: 26826
A8: Receivables | B8: -12895 | C8: -9737 | D8: -9450 | E8: -2471 | F8: -14501 | G8: -9241 | H8: -11278 | I8: 3012 | J8: -9852 | K8: -4495 | L8: -10643 | M8: -9252
A9: Inventory | B9: -209 | C9: -983 | D9: 217 | E9: 1510 | F9: -642 | G9: 331 | H9: 353 | I9: 349 | J9: -74 | K9: -476 | L9: 245 | M9: -540
A10: Payables | B10: 4172 | C10: 9120 | D10: 9308 | E10: 5307 | F10: 11727 | G10: 6819 | H10: 3134 | I10: 2220 | J10: 9678 | K10: 5413 | L10: 14601 | M10: 9683
A11: Loans Advances | B11: -6448 | C11: -6984 | D11: -10585 | E11: -5744 | F11: -16459 | G11: -13855 | H11: 7 | I11: 4618 | J11: 5005 | K11: 4937 | L11: -5588 | M11: -11956
A12: Working capital changes | B12: -15380 | C12: -8584 | D12: -10510 | E12: -1398 | F12: -19876 | G12: -15946 | H12: -7784 | I12: 10198 | J12: 4757 | K12: 5379 | L12: -1385 | M12: -12064
A13: Direct taxes | B13: -2947 | C13: -2979 | D13: -3215 | E13: -3202 | F13: -3403 | G13: -4883 | H13: -4046 | I13: -3471 | J13: -4539 | K13: -5127 | L13: -5280 | M13: -5601
A15: Cash from Investing Activity - | B15: -5510 | C15: -4778 | D15: -4627 | E15: -9796 | F15: 3914 | G15: -11023 | H15: -8408 | I15: -5750 | J15: -3585 | K15: -8048 | L15: 2179 | M15: -15489
A16: Fixed assets purchased | B16: -6967 | C16: -6252 | D16: -4322 | E16: -2977 | F16: -2877 | G16: -4307 | H16: -3437 | I16: -1808 | J16: -3111 | K16: -4144 | L16: -4517 | M16: -4419
A17: Fixed assets sold | B17: 289 | C17: 158 | D17: 198 | E17: 156 | F17: 862 | G17: 808 | H17: 137 | I17: 885 | J17: 71 | K17: 350 | L17: 306 | M17: 878
... A35: Net Cash Flow | B35: 483 | C35: 1759 | D35: -613 | E35: -245 | F35: 3254 | G35: -338 | H35: 4658 | I35: 2049 | J35: 397 | K35: 3156 | L35: -4968 | M35: 228
B46: Asset | C46: 2026 | D46: 27 | E46: 28 | F46: 29 | G46: 30
B47: Property, plant & equipment | C47: 0.0552 | D47: 0.0563 | E47: 0.0573 | F47: 0.0583 | G47: 0.059
B48: Investment property | C48: -0.1472 | D48: -0.1463 | E48: -0.1471 | F48: -0.1481 | G48: -0.1488
B49: Other intangible assets | C49: -0.0297 | D49: -0.03 | E49: -0.0303 | F49: -0.0305 | G49: -0.0308
B50: Right-of-use assets | C50: 0.0619 | D50: 0.0612 | E50: 0.0608 | F50: 0.0603 | G50: 0.0599
B51: Capital work-in-progress | C51: 0.2506 | D51: 0.2507 | E51: 0.2508 | F51: 0.2509 | G51: 0.2511
B52: Investment property under construction | C52: 0 | D52: 0 | E52: 0 | F52: 0 | G52: 0
B53: Goodwill | C53: =D75 -> 0.0086 | D53: =E75 -> 0.0086 | E53: =F75 -> 0.0086 | F53: =G75 -> 0.0086 | G53: =H75 -> 0.0086
B54: Intangible assets under development | C54: 0.1481 | D54: 0.1623 | E54: 0.1634 | F54: 0.1631 | G54: 0.1613
B55: Investments in joint ventures & associa | C55: -0.0347 | D55: -0.0347 | E55: -0.0347 | F55: -0.0347 | G55: -0.0347
B56: Other investments | C56: 0.1131 | D56: 0.1131 | E56: 0.1131 | F56: 0.1131 | G56: 0.1131
B57: Loans towards financing activities | C57: 0.0453 | D57: 0.0453 | E57: 0.0453 | F57: 0.0453 | G57: 0.0453
B58: Other loans | C58: 0.1913 | D58: 0.1913 | E58: 0.1913 | F58: 0.1913 | G58: 0.1913
B59: Other financial assets | C59: 0.0702 | D59: 0.0702 | E59: 0.0702 | F59: 0.0702 | G59: 0.0702
B60: Deferred tax assets (net) | C60: 0.089 | D60: 0.089 | E60: 0.089 | F60: 0.089 | G60: 0.089
B61: Current Tax Assets (net) | C61: 0.1265 | D61: 0.1265 | E61: 0.1265 | F61: 0.1265 | G61: 0.1265
B62: Other non-current assets | C62: -0.1823 | D62: -0.1823 | E62: -0.1823 | F62: -0.1823 | G62: -0.1823
C69: Property, plant & equipment | D69: 0.0554 | E69: 0.0554 | F69: 0.0554 | G69: 0.0554 | H69: 0.0554
C70: Investment property | D70: -0.2494 | E70: -0.2494 | F70: -0.2494 | G70: -0.2494 | H70: -0.2494
C71: Other intangible assets | D71: -0.0292 | E71: -0.0292 | F71: -0.0292 | G71: -0.0292 | H71: -0.0292
C72: Right-of-use assets | D72: 0.0915 | E72: 0.0915 | F72: 0.0915 | G72: 0.0915 | H72: 0.0915
C73: Capital work-in-progress | D73: 0.5752 | E73: 0.5752 | F73: 0.5752 | G73: 0.5752 | H73: 0.5752
C74: Investment property under construction | D74: 0.9669 | E74: 0.9669 | F74: 0.9669 | G74: 0.9669 | H74: 0.9669
C75: Goodwill | D75: 0.0086 | E75: 0.0086 | F75: 0.0086 | G75: 0.0086 | H75: 0.0086
C76: Intangible assets under development | D76: 0.1528 | E76: 0.1528 | F76: 0.1528 | G76: 0.1528 | H76: 0.1528
C77: Investments in joint ventures & associa | D77: tes -3.47% | E77: -0.0347 | F77: -0.0347 | G77: -0.0347 | H77: -0.0347
C78: Other investments | D78: 0.1131 | E78: 0.1131 | F78: 0.1131 | G78: 0.1131 | H78: 0.1131
C79: Loans towards financing activities | D79: 0.0453 | E79: 0.0453 | F79: 0.0453 | G79: 0.0453 | H79: 0.0453
C80: Other loans | D80: 0.1913 | E80: 0.1913 | F80: 0.1913 | G80: 0.1913 | H80: 0.1913
C81: Other financial assets | D81: 0.0702 | E81: 0.0702 | F81: 0.0702 | G81: 0.0702 | H81: 0.0702
C82: Deferred tax assets (net) | D82: 0.089 | E82: 0.089 | F82: 0.089 | G82: 0.089 | H82: 0.089
C83: Current Tax Assets (net) | D83: 0.1265 | E83: 0.1265 | F83: 0.1265 | G83: 0.1265 | H83: 0.1265
C84: Other non-current assets | D84: -0.1823 | E84: -0.1823 | F84: -0.1823 | G84: -0.1823 | H84: -0.1823
